{
  "timestamp": "2026-02-15T06:12:37.118Z",
  "projects": [
    {
      "id": 1771062269488,
      "name": "改修系",
      "client": "",
      "status": "planning",
      "collapsed": false,
      "sort_order": 0,
      "created_at": "2026-02-14T09:44:33.784785+00:00",
      "updated_at": "2026-02-14T09:44:33.784785+00:00"
    },
    {
      "id": 1771062241797,
      "name": "SOEシステムブログLP",
      "client": "",
      "status": "active",
      "collapsed": false,
      "sort_order": 1,
      "created_at": "2026-02-14T09:44:03.913739+00:00",
      "updated_at": "2026-02-14T09:44:03.913739+00:00"
    },
    {
      "id": 1771048223028,
      "name": "萩原（HP・採用）",
      "client": "",
      "status": "active",
      "collapsed": true,
      "sort_order": 2,
      "created_at": "2026-02-14T05:50:24.871188+00:00",
      "updated_at": "2026-02-14T05:50:24.871188+00:00"
    },
    {
      "id": 1771048146478,
      "name": "高野工業",
      "client": "",
      "status": "active",
      "collapsed": false,
      "sort_order": 3,
      "created_at": "2026-02-14T05:49:08.599911+00:00",
      "updated_at": "2026-02-14T05:49:08.599911+00:00"
    },
    {
      "id": 1771047702705,
      "name": "アクティブアスベスト",
      "client": "",
      "status": "active",
      "collapsed": false,
      "sort_order": 4,
      "created_at": "2026-02-14T05:41:45.143682+00:00",
      "updated_at": "2026-02-14T05:41:45.143682+00:00"
    },
    {
      "id": 1771047215241,
      "name": "両備HM風の野LP",
      "client": "",
      "status": "active",
      "collapsed": false,
      "sort_order": 5,
      "created_at": "2026-02-14T05:33:37.025963+00:00",
      "updated_at": "2026-02-14T05:33:37.025963+00:00"
    },
    {
      "id": 1771047174687,
      "name": "両備HM津島福居LP",
      "client": "",
      "status": "active",
      "collapsed": false,
      "sort_order": 6,
      "created_at": "2026-02-14T05:32:56.593255+00:00",
      "updated_at": "2026-02-14T05:32:56.593255+00:00"
    },
    {
      "id": 1771047136752,
      "name": "三宅医院",
      "client": "",
      "status": "active",
      "collapsed": false,
      "sort_order": 7,
      "created_at": "2026-02-14T05:32:18.920165+00:00",
      "updated_at": "2026-02-14T05:32:18.920165+00:00"
    },
    {
      "id": 1771046938995,
      "name": "重藤組HP",
      "client": "",
      "status": "active",
      "collapsed": false,
      "sort_order": 8,
      "created_at": "2026-02-14T05:29:00.798859+00:00",
      "updated_at": "2026-02-14T05:29:00.798859+00:00"
    },
    {
      "id": 1771046571829,
      "name": "Ray ECサイトリニューアル",
      "client": "",
      "status": "planning",
      "collapsed": false,
      "sort_order": 9,
      "created_at": "2026-02-14T05:22:59.485898+00:00",
      "updated_at": "2026-02-14T05:22:59.485898+00:00"
    },
    {
      "id": 1771045915922,
      "name": "両備ホームズ採用パンフレット",
      "client": "",
      "status": "active",
      "collapsed": false,
      "sort_order": 10,
      "created_at": "2026-02-14T05:11:58.654194+00:00",
      "updated_at": "2026-02-14T05:11:58.654194+00:00"
    },
    {
      "id": 1771044832283,
      "name": "oneunity2パンフレット",
      "client": "",
      "status": "active",
      "collapsed": false,
      "sort_order": 11,
      "created_at": "2026-02-14T04:53:54.154889+00:00",
      "updated_at": "2026-02-14T04:53:54.154889+00:00"
    },
    {
      "id": 1771044296039,
      "name": "グリッジ採用LP",
      "client": "",
      "status": "active",
      "collapsed": false,
      "sort_order": 12,
      "created_at": "2026-02-14T04:44:57.671538+00:00",
      "updated_at": "2026-02-14T04:44:57.671538+00:00"
    },
    {
      "id": 1771039129808,
      "name": "両備ホームズイベント制作",
      "client": "",
      "status": "planning",
      "collapsed": false,
      "sort_order": 13,
      "created_at": "2026-02-14T03:34:47.725541+00:00",
      "updated_at": "2026-02-14T03:34:47.725541+00:00"
    },
    {
      "id": 1771046274008,
      "name": "両備ホームズ管理",
      "client": "",
      "status": "planning",
      "collapsed": false,
      "sort_order": 14,
      "created_at": "2026-02-14T05:18:00.030114+00:00",
      "updated_at": "2026-02-14T05:18:00.030114+00:00"
    },
    {
      "id": 1771043105398,
      "name": "両備ホームズ制作物全般",
      "client": "",
      "status": "planning",
      "collapsed": false,
      "sort_order": 15,
      "created_at": "2026-02-14T04:25:07.004975+00:00",
      "updated_at": "2026-02-14T04:25:07.004975+00:00"
    }
  ],
  "tasks": [
    {
      "id": "1771062269488-1771069350431",
      "project_id": 1771062269488,
      "name": "アクティブ改修",
      "phase": "wire",
      "assignee": "nishitani",
      "start_date": "2026-02-16",
      "end_date": "2026-02-20",
      "done": false,
      "task_status": "inbox",
      "description": "",
      "comments": [],
      "estimated_hours": 3,
      "task_type": null,
      "created_at": "2026-02-14T11:42:32.312492+00:00",
      "updated_at": "2026-02-14T11:42:32.312492+00:00",
      "dependencies": [],
      "include_weekends": false
    },
    {
      "id": "1771062269488-1771069469659",
      "project_id": 1771062269488,
      "name": "アクティブバナー作成（3パターン・5サイズ）",
      "phase": "wire",
      "assignee": "nakata",
      "start_date": "2026-03-02",
      "end_date": "2026-03-03",
      "done": false,
      "task_status": "inbox",
      "description": "",
      "comments": [],
      "estimated_hours": 8,
      "task_type": null,
      "created_at": "2026-02-14T11:44:40.698108+00:00",
      "updated_at": "2026-02-14T11:44:40.698108+00:00",
      "dependencies": [],
      "include_weekends": false
    },
    {
      "id": "1771062269488-1771084352927",
      "project_id": 1771062269488,
      "name": "重藤組インスタ採用バナー",
      "phase": "wire",
      "assignee": "nakata",
      "start_date": "2026-02-26",
      "end_date": "2026-02-27",
      "done": false,
      "task_status": "inbox",
      "description": "",
      "comments": [],
      "estimated_hours": null,
      "task_type": null,
      "created_at": "2026-02-14T15:52:35.054244+00:00",
      "updated_at": "2026-02-14T15:52:35.054244+00:00",
      "dependencies": [],
      "include_weekends": false
    },
    {
      "id": "1771062241797-0",
      "project_id": 1771062241797,
      "name": "SOEシステムブログLP ラフ案提出",
      "phase": "design",
      "assignee": "imashige",
      "start_date": "2026-02-18",
      "end_date": "2026-02-18",
      "done": false,
      "task_status": "todo",
      "description": "",
      "comments": [],
      "estimated_hours": null,
      "task_type": "milestone",
      "created_at": "2026-02-14T09:44:04.189052+00:00",
      "updated_at": "2026-02-14T09:44:04.189052+00:00",
      "dependencies": [],
      "include_weekends": false
    },
    {
      "id": "1771062241797-1",
      "project_id": 1771062241797,
      "name": "SOEシステムブログLP ラフ案修正指示",
      "phase": "design",
      "assignee": "client",
      "start_date": "2026-02-27",
      "end_date": "2026-02-27",
      "done": false,
      "task_status": "todo",
      "description": "",
      "comments": [],
      "estimated_hours": null,
      "task_type": "milestone",
      "created_at": "2026-02-14T09:44:04.189052+00:00",
      "updated_at": "2026-02-14T09:44:04.189052+00:00",
      "dependencies": [],
      "include_weekends": false
    },
    {
      "id": "1771062241797-2",
      "project_id": 1771062241797,
      "name": "SOEシステムブログLP 清書",
      "phase": "design",
      "assignee": "imashige",
      "start_date": "2026-03-04",
      "end_date": "2026-03-06",
      "done": false,
      "task_status": "todo",
      "description": "",
      "comments": [],
      "estimated_hours": null,
      "task_type": null,
      "created_at": "2026-02-14T09:44:04.189052+00:00",
      "updated_at": "2026-02-14T09:44:04.189052+00:00",
      "dependencies": [],
      "include_weekends": false
    },
    {
      "id": "1771062241797-3",
      "project_id": 1771062241797,
      "name": "SOEシステムブログLP デザイン調整",
      "phase": "design",
      "assignee": "nakata",
      "start_date": "2026-03-05",
      "end_date": "2026-03-06",
      "done": false,
      "task_status": "todo",
      "description": "テスト\n\n",
      "comments": [
        {
          "id": 1771062602676,
          "text": "テスト",
          "time": "18:50",
          "author": "shimizu"
        }
      ],
      "estimated_hours": null,
      "task_type": null,
      "created_at": "2026-02-14T09:44:04.189052+00:00",
      "updated_at": "2026-02-14T09:44:04.189052+00:00",
      "dependencies": [],
      "include_weekends": false
    },
    {
      "id": "1771062241797-4",
      "project_id": 1771062241797,
      "name": "SOEシステムブログLP デモページ提出（デザイン込）",
      "phase": "design",
      "assignee": "imashige",
      "start_date": "2026-03-13",
      "end_date": "2026-03-13",
      "done": false,
      "task_status": "todo",
      "description": "",
      "comments": [],
      "estimated_hours": null,
      "task_type": "milestone",
      "created_at": "2026-02-14T09:44:04.189052+00:00",
      "updated_at": "2026-02-14T09:44:04.189052+00:00",
      "dependencies": [],
      "include_weekends": false
    },
    {
      "id": "1771062241797-5",
      "project_id": 1771062241797,
      "name": "SOEシステムブログLP デモページ修正指示",
      "phase": "design",
      "assignee": "client",
      "start_date": "2026-03-20",
      "end_date": "2026-03-20",
      "done": false,
      "task_status": "todo",
      "description": "",
      "comments": [],
      "estimated_hours": null,
      "task_type": "milestone",
      "created_at": "2026-02-14T09:44:04.189052+00:00",
      "updated_at": "2026-02-14T09:44:04.189052+00:00",
      "dependencies": [],
      "include_weekends": false
    },
    {
      "id": "1771062241797-6",
      "project_id": 1771062241797,
      "name": "SOEシステムブログLP 公開",
      "phase": "design",
      "assignee": "imashige",
      "start_date": "2026-03-27",
      "end_date": "2026-03-27",
      "done": false,
      "task_status": "todo",
      "description": "",
      "comments": [],
      "estimated_hours": null,
      "task_type": "milestone",
      "created_at": "2026-02-14T09:44:04.189052+00:00",
      "updated_at": "2026-02-14T09:44:04.189052+00:00",
      "dependencies": [],
      "include_weekends": false
    },
    {
      "id": "1771048223028-1771048318946",
      "project_id": 1771048223028,
      "name": "萩原（HP・採用） ライティング",
      "phase": "wire",
      "assignee": "imashige",
      "start_date": "2026-03-09",
      "end_date": "2026-03-13",
      "done": false,
      "task_status": "inbox",
      "description": "",
      "comments": [],
      "estimated_hours": null,
      "task_type": null,
      "created_at": "2026-02-14T05:52:01.517668+00:00",
      "updated_at": "2026-02-14T05:52:01.517668+00:00",
      "dependencies": [],
      "include_weekends": false
    },
    {
      "id": "1771048409595-6",
      "project_id": 1771048223028,
      "name": "萩原（HP・採用） デモサイト最終修正",
      "phase": "design",
      "assignee": "nishitani",
      "start_date": "2026-07-08",
      "end_date": "2026-07-08",
      "done": false,
      "task_status": "todo",
      "description": "",
      "comments": [],
      "estimated_hours": null,
      "task_type": "milestone",
      "created_at": "2026-02-14T05:53:31.484455+00:00",
      "updated_at": "2026-02-14T05:53:31.484455+00:00",
      "dependencies": [],
      "include_weekends": false
    },
    {
      "id": "1771048409595-1",
      "project_id": 1771048223028,
      "name": "萩原（HP・採用） コーディング",
      "phase": "design",
      "assignee": "nishitani",
      "start_date": "2026-05-18",
      "end_date": "2026-06-05",
      "done": false,
      "task_status": "todo",
      "description": "",
      "comments": [],
      "estimated_hours": null,
      "task_type": null,
      "created_at": "2026-02-14T05:53:31.484455+00:00",
      "updated_at": "2026-02-14T05:53:31.484455+00:00",
      "dependencies": [],
      "include_weekends": false
    },
    {
      "id": "1771048409595-3",
      "project_id": 1771048223028,
      "name": "萩原（HP・採用） デモサイト社内提出",
      "phase": "design",
      "assignee": "nishitani",
      "start_date": "2026-06-17",
      "end_date": "2026-06-17",
      "done": false,
      "task_status": "todo",
      "description": "",
      "comments": [],
      "estimated_hours": null,
      "task_type": "milestone",
      "created_at": "2026-02-14T05:53:31.484455+00:00",
      "updated_at": "2026-02-14T05:53:31.484455+00:00",
      "dependencies": [],
      "include_weekends": false
    },
    {
      "id": "1771048409595-4",
      "project_id": 1771048223028,
      "name": "萩原（HP・採用） デモサイト提出",
      "phase": "design",
      "assignee": "nishitani",
      "start_date": "2026-06-19",
      "end_date": "2026-06-19",
      "done": false,
      "task_status": "todo",
      "description": "",
      "comments": [],
      "estimated_hours": null,
      "task_type": "milestone",
      "created_at": "2026-02-14T05:53:31.484455+00:00",
      "updated_at": "2026-02-14T05:53:31.484455+00:00",
      "dependencies": [],
      "include_weekends": false
    },
    {
      "id": "1771047174687-0",
      "project_id": 1771047174687,
      "name": "両備HM津島福居LP トップページデザイン",
      "phase": "design",
      "assignee": "fujii",
      "start_date": "2026-02-16",
      "end_date": "2026-02-17",
      "done": false,
      "task_status": "todo",
      "description": "",
      "comments": [],
      "estimated_hours": null,
      "task_type": null,
      "created_at": "2026-02-14T05:32:56.819472+00:00",
      "updated_at": "2026-02-14T05:32:56.819472+00:00",
      "dependencies": [],
      "include_weekends": false
    },
    {
      "id": "1771047174687-1",
      "project_id": 1771047174687,
      "name": "両備HM津島福居LP 初稿デザイン提出",
      "phase": "design",
      "assignee": "fujii",
      "start_date": "2026-02-18",
      "end_date": "2026-02-18",
      "done": false,
      "task_status": "todo",
      "description": "",
      "comments": [],
      "estimated_hours": null,
      "task_type": "milestone",
      "created_at": "2026-02-14T05:32:56.819472+00:00",
      "updated_at": "2026-02-14T05:32:56.819472+00:00",
      "dependencies": [],
      "include_weekends": false
    },
    {
      "id": "1771047174687-2",
      "project_id": 1771047174687,
      "name": "両備HM津島福居LP 初稿デザイン提出",
      "phase": "design",
      "assignee": "fujii",
      "start_date": "2026-02-20",
      "end_date": "2026-02-20",
      "done": false,
      "task_status": "todo",
      "description": "",
      "comments": [],
      "estimated_hours": null,
      "task_type": "milestone",
      "created_at": "2026-02-14T05:32:56.819472+00:00",
      "updated_at": "2026-02-14T05:32:56.819472+00:00",
      "dependencies": [],
      "include_weekends": false
    },
    {
      "id": "1771047174687-3",
      "project_id": 1771047174687,
      "name": "(〆両備HM津島福居LP 初稿デザイン修正指示）",
      "phase": "design",
      "assignee": "client",
      "start_date": "2026-02-25",
      "end_date": "2026-02-25",
      "done": false,
      "task_status": "todo",
      "description": "",
      "comments": [],
      "estimated_hours": null,
      "task_type": "milestone",
      "created_at": "2026-02-14T05:32:56.819472+00:00",
      "updated_at": "2026-02-14T05:32:56.819472+00:00",
      "dependencies": [],
      "include_weekends": false
    },
    {
      "id": "1771046938995-14",
      "project_id": 1771046938995,
      "name": "重藤組HP 全体デザイン修正指示",
      "phase": "design",
      "assignee": "client",
      "start_date": "2026-04-17",
      "end_date": "2026-04-17",
      "done": false,
      "task_status": "todo",
      "description": "",
      "comments": [],
      "estimated_hours": null,
      "task_type": "milestone",
      "created_at": "2026-02-14T05:29:01.014397+00:00",
      "updated_at": "2026-02-14T05:29:01.014397+00:00",
      "dependencies": [],
      "include_weekends": false
    },
    {
      "id": "1771045915922-5",
      "project_id": 1771045915922,
      "name": "両備ホームズ採用パンフレット 入稿",
      "phase": "design",
      "assignee": "fujii",
      "start_date": "2026-03-20",
      "end_date": "2026-03-20",
      "done": false,
      "task_status": "todo",
      "description": "",
      "comments": [],
      "estimated_hours": null,
      "task_type": "milestone",
      "created_at": "2026-02-14T05:11:58.956749+00:00",
      "updated_at": "2026-02-14T05:11:58.956749+00:00",
      "dependencies": [],
      "include_weekends": false
    },
    {
      "id": "1771062269488-1771062336721",
      "project_id": 1771062269488,
      "name": "スマイル産業実績作成",
      "phase": "wire",
      "assignee": "imashige",
      "start_date": "2026-02-19",
      "end_date": "2026-02-19",
      "done": false,
      "task_status": "inbox",
      "description": "",
      "comments": [],
      "estimated_hours": null,
      "task_type": null,
      "created_at": "2026-02-14T09:45:39.536422+00:00",
      "updated_at": "2026-02-14T09:45:39.536422+00:00",
      "dependencies": [],
      "include_weekends": false
    },
    {
      "id": "1771048223028-6",
      "project_id": 1771048223028,
      "name": "(〆萩原（HP・採用） 初稿デザイン修正指示）",
      "phase": "design",
      "assignee": "client",
      "start_date": "2026-04-03",
      "end_date": "2026-04-03",
      "done": false,
      "task_status": "todo",
      "description": "",
      "comments": [],
      "estimated_hours": null,
      "task_type": "milestone",
      "created_at": "2026-02-14T05:50:25.052033+00:00",
      "updated_at": "2026-02-14T05:50:25.052033+00:00",
      "dependencies": [],
      "include_weekends": false
    },
    {
      "id": "1771048223028-7",
      "project_id": 1771048223028,
      "name": "萩原（HP・採用） 初稿デザイン提出",
      "phase": "design",
      "assignee": "fujii",
      "start_date": "2026-03-18",
      "end_date": "2026-03-18",
      "done": false,
      "task_status": "todo",
      "description": "",
      "comments": [],
      "estimated_hours": null,
      "task_type": "milestone",
      "created_at": "2026-02-14T05:50:25.052033+00:00",
      "updated_at": "2026-02-14T05:50:25.052033+00:00",
      "dependencies": [],
      "include_weekends": false
    },
    {
      "id": "1771048223028-8",
      "project_id": 1771048223028,
      "name": "萩原（HP・採用） 全体ページデザイン 1/2",
      "phase": "design",
      "assignee": "fujii",
      "start_date": "2026-04-06",
      "end_date": "2026-04-10",
      "done": false,
      "task_status": "todo",
      "description": "",
      "comments": [],
      "estimated_hours": null,
      "task_type": null,
      "created_at": "2026-02-14T05:50:25.052033+00:00",
      "updated_at": "2026-02-14T05:50:25.052033+00:00",
      "dependencies": [],
      "include_weekends": false
    },
    {
      "id": "1771047702705-5",
      "project_id": 1771047702705,
      "name": "アクティブアスベスト デモサイト最終修正",
      "phase": "design",
      "assignee": "nishitani",
      "start_date": "2026-03-04",
      "end_date": "2026-03-04",
      "done": false,
      "task_status": "todo",
      "description": "",
      "comments": [],
      "estimated_hours": null,
      "task_type": "milestone",
      "created_at": "2026-02-14T05:41:45.377527+00:00",
      "updated_at": "2026-02-14T05:41:45.377527+00:00",
      "dependencies": [],
      "include_weekends": false
    },
    {
      "id": "1771047702705-6",
      "project_id": 1771047702705,
      "name": "アクティブアスベスト 公開",
      "phase": "design",
      "assignee": "nishitani",
      "start_date": "2026-03-06",
      "end_date": "2026-03-06",
      "done": false,
      "task_status": "todo",
      "description": "",
      "comments": [],
      "estimated_hours": null,
      "task_type": "milestone",
      "created_at": "2026-02-14T05:41:45.377527+00:00",
      "updated_at": "2026-02-14T05:41:45.377527+00:00",
      "dependencies": [],
      "include_weekends": false
    },
    {
      "id": "1771047215241-7",
      "project_id": 1771047215241,
      "name": "両備HM風の野LP デモサイト提出",
      "phase": "design",
      "assignee": "nishitani",
      "start_date": "2026-03-10",
      "end_date": "2026-03-10",
      "done": false,
      "task_status": "todo",
      "description": "",
      "comments": [],
      "estimated_hours": null,
      "task_type": "milestone",
      "created_at": "2026-02-14T05:33:37.260611+00:00",
      "updated_at": "2026-02-14T05:33:37.260611+00:00",
      "dependencies": [],
      "include_weekends": false
    },
    {
      "id": "1771047215241-6",
      "project_id": 1771047215241,
      "name": "両備HM風の野LP デモサイト社内提出",
      "phase": "design",
      "assignee": "nishitani",
      "start_date": "2026-03-06",
      "end_date": "2026-03-06",
      "done": false,
      "task_status": "todo",
      "description": "",
      "comments": [],
      "estimated_hours": null,
      "task_type": "milestone",
      "created_at": "2026-02-14T05:33:37.260611+00:00",
      "updated_at": "2026-02-14T05:33:37.260611+00:00",
      "dependencies": [],
      "include_weekends": false
    },
    {
      "id": "1771047174687-4",
      "project_id": 1771047174687,
      "name": "両備HM津島福居LP 全体ページデザイン",
      "phase": "design",
      "assignee": "fujii",
      "start_date": "2026-02-26",
      "end_date": "2026-02-27",
      "done": false,
      "task_status": "todo",
      "description": "",
      "comments": [],
      "estimated_hours": null,
      "task_type": null,
      "created_at": "2026-02-14T05:32:56.819472+00:00",
      "updated_at": "2026-02-14T05:32:56.819472+00:00",
      "dependencies": [],
      "include_weekends": false
    },
    {
      "id": "1771047174687-5",
      "project_id": 1771047174687,
      "name": "両備HM津島福居LP 全体デザイン提出",
      "phase": "design",
      "assignee": "fujii",
      "start_date": "2026-03-04",
      "end_date": "2026-03-04",
      "done": false,
      "task_status": "todo",
      "description": "",
      "comments": [],
      "estimated_hours": null,
      "task_type": "milestone",
      "created_at": "2026-02-14T05:32:56.819472+00:00",
      "updated_at": "2026-02-14T05:32:56.819472+00:00",
      "dependencies": [],
      "include_weekends": false
    },
    {
      "id": "1771047174687-6",
      "project_id": 1771047174687,
      "name": "両備HM津島福居LP 全体デザイン提出",
      "phase": "design",
      "assignee": "fujii",
      "start_date": "2026-03-06",
      "end_date": "2026-03-06",
      "done": false,
      "task_status": "todo",
      "description": "",
      "comments": [],
      "estimated_hours": null,
      "task_type": "milestone",
      "created_at": "2026-02-14T05:32:56.819472+00:00",
      "updated_at": "2026-02-14T05:32:56.819472+00:00",
      "dependencies": [],
      "include_weekends": false
    },
    {
      "id": "1771044832283-10",
      "project_id": 1771044832283,
      "name": "oneunity2パンフレット 最終確認",
      "phase": "design",
      "assignee": "member_1771061146147",
      "start_date": "2026-04-10",
      "end_date": "2026-04-10",
      "done": false,
      "task_status": "todo",
      "description": "",
      "comments": [],
      "estimated_hours": null,
      "task_type": "milestone",
      "created_at": "2026-02-14T04:53:54.431497+00:00",
      "updated_at": "2026-02-14T04:53:54.431497+00:00",
      "dependencies": [],
      "include_weekends": false
    },
    {
      "id": "1771044832283-3",
      "project_id": 1771044832283,
      "name": "oneunity2パンフレット デザイン修正指示",
      "phase": "design",
      "assignee": "client",
      "start_date": "2026-03-13",
      "end_date": "2026-03-13",
      "done": false,
      "task_status": "todo",
      "description": "",
      "comments": [],
      "estimated_hours": null,
      "task_type": "milestone",
      "created_at": "2026-02-14T04:53:54.431497+00:00",
      "updated_at": "2026-02-14T04:53:54.431497+00:00",
      "dependencies": [],
      "include_weekends": false
    },
    {
      "id": "1771044832283-4",
      "project_id": 1771044832283,
      "name": "oneunity2パンフレット 全体デザイン作成 1/2",
      "phase": "design",
      "assignee": "member_1771061146147",
      "start_date": "2026-03-16",
      "end_date": "2026-03-20",
      "done": false,
      "task_status": "todo",
      "description": "",
      "comments": [],
      "estimated_hours": null,
      "task_type": null,
      "created_at": "2026-02-14T04:53:54.431497+00:00",
      "updated_at": "2026-02-14T04:53:54.431497+00:00",
      "dependencies": [],
      "include_weekends": false
    },
    {
      "id": "1771044832283-5",
      "project_id": 1771044832283,
      "name": "oneunity2パンフレット 全体デザイン作成 1/2",
      "phase": "design",
      "assignee": "member_1771061146147",
      "start_date": "2026-03-23",
      "end_date": "2026-03-27",
      "done": false,
      "task_status": "todo",
      "description": "",
      "comments": [],
      "estimated_hours": null,
      "task_type": null,
      "created_at": "2026-02-14T04:53:54.431497+00:00",
      "updated_at": "2026-02-14T04:53:54.431497+00:00",
      "dependencies": [],
      "include_weekends": false
    },
    {
      "id": "1771044832283-6",
      "project_id": 1771044832283,
      "name": "oneunity2パンフレット デザイン提出",
      "phase": "design",
      "assignee": "fujii",
      "start_date": "2026-04-01",
      "end_date": "2026-04-01",
      "done": false,
      "task_status": "todo",
      "description": "",
      "comments": [],
      "estimated_hours": null,
      "task_type": "milestone",
      "created_at": "2026-02-14T04:53:54.431497+00:00",
      "updated_at": "2026-02-14T04:53:54.431497+00:00",
      "dependencies": [],
      "include_weekends": false
    },
    {
      "id": "1771044832283-8",
      "project_id": 1771044832283,
      "name": "oneunity2パンフレット 最終調整",
      "phase": "design",
      "assignee": "member_1771061146147",
      "start_date": "2026-04-09",
      "end_date": "2026-04-10",
      "done": false,
      "task_status": "todo",
      "description": "",
      "comments": [],
      "estimated_hours": null,
      "task_type": null,
      "created_at": "2026-02-14T04:53:54.431497+00:00",
      "updated_at": "2026-02-14T04:53:54.431497+00:00",
      "dependencies": [],
      "include_weekends": false
    },
    {
      "id": "1771044832283-9",
      "project_id": 1771044832283,
      "name": "oneunity2パンフレット デザイン修正指示",
      "phase": "design",
      "assignee": "client",
      "start_date": "2026-04-08",
      "end_date": "2026-04-08",
      "done": false,
      "task_status": "todo",
      "description": "",
      "comments": [],
      "estimated_hours": null,
      "task_type": "milestone",
      "created_at": "2026-02-14T04:53:54.431497+00:00",
      "updated_at": "2026-02-14T04:53:54.431497+00:00",
      "dependencies": [],
      "include_weekends": false
    },
    {
      "id": "1771044296039-10",
      "project_id": 1771044296039,
      "name": "グリッジ採用LP 全体デザイン提出",
      "phase": "design",
      "assignee": "nakata",
      "start_date": "2026-04-17",
      "end_date": "2026-04-17",
      "done": false,
      "task_status": "todo",
      "description": "",
      "comments": [],
      "estimated_hours": null,
      "task_type": "milestone",
      "created_at": "2026-02-14T04:44:57.863188+00:00",
      "updated_at": "2026-02-14T04:44:57.863188+00:00",
      "dependencies": [],
      "include_weekends": false
    },
    {
      "id": "1771044296039-11",
      "project_id": 1771044296039,
      "name": "グリッジ採用LP ライター原稿提出・写真提出",
      "phase": "design",
      "assignee": "shimizu",
      "start_date": "2026-04-24",
      "end_date": "2026-04-24",
      "done": false,
      "task_status": "todo",
      "description": "",
      "comments": [],
      "estimated_hours": null,
      "task_type": "milestone",
      "created_at": "2026-02-14T04:44:57.863188+00:00",
      "updated_at": "2026-02-14T04:44:57.863188+00:00",
      "dependencies": [],
      "include_weekends": false
    },
    {
      "id": "1771044296039-17",
      "project_id": 1771044296039,
      "name": "グリッジ採用LP デモサイト最終修正",
      "phase": "design",
      "assignee": "client",
      "start_date": "2026-05-20",
      "end_date": "2026-05-20",
      "done": false,
      "task_status": "todo",
      "description": "",
      "comments": [],
      "estimated_hours": null,
      "task_type": "milestone",
      "created_at": "2026-02-14T04:44:57.863188+00:00",
      "updated_at": "2026-02-14T04:44:57.863188+00:00",
      "dependencies": [],
      "include_weekends": false
    },
    {
      "id": "1771047215241-0",
      "project_id": 1771047215241,
      "name": "両備HM風の野LP 全体ページデザイン",
      "phase": "design",
      "assignee": "fujii",
      "start_date": "2026-02-09",
      "end_date": "2026-02-13",
      "done": false,
      "task_status": "todo",
      "description": "",
      "comments": [],
      "estimated_hours": null,
      "task_type": null,
      "created_at": "2026-02-14T05:33:37.260611+00:00",
      "updated_at": "2026-02-14T05:33:37.260611+00:00",
      "dependencies": [],
      "include_weekends": false
    },
    {
      "id": "1771047174687-9",
      "project_id": 1771047174687,
      "name": "両備HM津島福居LP デモサイト提出",
      "phase": "design",
      "assignee": "nishitani",
      "start_date": "2026-03-27",
      "end_date": "2026-03-27",
      "done": false,
      "task_status": "todo",
      "description": "",
      "comments": [],
      "estimated_hours": null,
      "task_type": "milestone",
      "created_at": "2026-02-14T05:32:56.819472+00:00",
      "updated_at": "2026-02-14T05:32:56.819472+00:00",
      "dependencies": [],
      "include_weekends": false
    },
    {
      "id": "1771047174687-10",
      "project_id": 1771047174687,
      "name": "両備HM津島福居LP デモサイト社内提出",
      "phase": "design",
      "assignee": "nishitani",
      "start_date": "2026-03-25",
      "end_date": "2026-03-25",
      "done": false,
      "task_status": "todo",
      "description": "",
      "comments": [],
      "estimated_hours": null,
      "task_type": "milestone",
      "created_at": "2026-02-14T05:32:56.819472+00:00",
      "updated_at": "2026-02-14T05:32:56.819472+00:00",
      "dependencies": [],
      "include_weekends": false
    },
    {
      "id": "1771047174687-11",
      "project_id": 1771047174687,
      "name": "両備HM津島福居LP デモサイト最終修正",
      "phase": "design",
      "assignee": "nishitani",
      "start_date": "2026-04-02",
      "end_date": "2026-04-03",
      "done": false,
      "task_status": "todo",
      "description": "",
      "comments": [],
      "estimated_hours": null,
      "task_type": null,
      "created_at": "2026-02-14T05:32:56.819472+00:00",
      "updated_at": "2026-02-14T05:32:56.819472+00:00",
      "dependencies": [],
      "include_weekends": false
    },
    {
      "id": "1771047174687-12",
      "project_id": 1771047174687,
      "name": "両備HM津島福居LP デモサイト最終修正",
      "phase": "design",
      "assignee": "client",
      "start_date": "2026-04-01",
      "end_date": "2026-04-01",
      "done": false,
      "task_status": "todo",
      "description": "",
      "comments": [],
      "estimated_hours": null,
      "task_type": "milestone",
      "created_at": "2026-02-14T05:32:56.819472+00:00",
      "updated_at": "2026-02-14T05:32:56.819472+00:00",
      "dependencies": [],
      "include_weekends": false
    },
    {
      "id": "1771047174687-13",
      "project_id": 1771047174687,
      "name": "両備HM津島福居LP 公開",
      "phase": "design",
      "assignee": "nishitani",
      "start_date": "2026-04-03",
      "end_date": "2026-04-03",
      "done": false,
      "task_status": "todo",
      "description": "",
      "comments": [],
      "estimated_hours": null,
      "task_type": "milestone",
      "created_at": "2026-02-14T05:32:56.819472+00:00",
      "updated_at": "2026-02-14T05:32:56.819472+00:00",
      "dependencies": [],
      "include_weekends": false
    },
    {
      "id": "1771047136752-0",
      "project_id": 1771047136752,
      "name": "三宅医院 初稿案デザイン（kana）",
      "phase": "design",
      "assignee": "member_1771048866898",
      "start_date": "2026-02-16",
      "end_date": "2026-02-18",
      "done": false,
      "task_status": "todo",
      "description": "",
      "comments": [],
      "estimated_hours": null,
      "task_type": null,
      "created_at": "2026-02-14T05:32:19.184922+00:00",
      "updated_at": "2026-02-14T05:32:19.184922+00:00",
      "dependencies": [],
      "include_weekends": false
    },
    {
      "id": "1771046938995-18",
      "project_id": 1771046938995,
      "name": "重藤組HP デモサイト提出",
      "phase": "design",
      "assignee": "nishitani",
      "start_date": "2026-05-15",
      "end_date": "2026-05-15",
      "done": false,
      "task_status": "todo",
      "description": "",
      "comments": [],
      "estimated_hours": null,
      "task_type": "milestone",
      "created_at": "2026-02-14T05:29:01.014397+00:00",
      "updated_at": "2026-02-14T05:29:01.014397+00:00",
      "dependencies": [],
      "include_weekends": false
    },
    {
      "id": "1771046938995-19",
      "project_id": 1771046938995,
      "name": "重藤組HP デモサイト最終修正",
      "phase": "design",
      "assignee": "client",
      "start_date": "2026-05-22",
      "end_date": "2026-05-22",
      "done": false,
      "task_status": "todo",
      "description": "",
      "comments": [],
      "estimated_hours": null,
      "task_type": "milestone",
      "created_at": "2026-02-14T05:29:01.014397+00:00",
      "updated_at": "2026-02-14T05:29:01.014397+00:00",
      "dependencies": [],
      "include_weekends": false
    },
    {
      "id": "1771046938995-20",
      "project_id": 1771046938995,
      "name": "重藤組HP 公開",
      "phase": "design",
      "assignee": "nishitani",
      "start_date": "2026-05-29",
      "end_date": "2026-05-29",
      "done": false,
      "task_status": "todo",
      "description": "",
      "comments": [],
      "estimated_hours": null,
      "task_type": "milestone",
      "created_at": "2026-02-14T05:29:01.014397+00:00",
      "updated_at": "2026-02-14T05:29:01.014397+00:00",
      "dependencies": [],
      "include_weekends": false
    },
    {
      "id": "1771046571829-1771046598614",
      "project_id": 1771046571829,
      "name": "Ray 実装 4/4",
      "phase": "wire",
      "assignee": "nishitani",
      "start_date": "2026-02-23",
      "end_date": "2026-02-27",
      "done": false,
      "task_status": "inbox",
      "description": "",
      "comments": [],
      "estimated_hours": null,
      "task_type": null,
      "created_at": "2026-02-14T05:23:23.414526+00:00",
      "updated_at": "2026-02-14T05:23:23.414526+00:00",
      "dependencies": [],
      "include_weekends": false
    },
    {
      "id": "1771046571829-1771046608126",
      "project_id": 1771046571829,
      "name": "デモサイトクライアント提出",
      "phase": "wire",
      "assignee": "nishitani",
      "start_date": "2026-02-27",
      "end_date": "2026-02-27",
      "done": false,
      "task_status": "inbox",
      "description": "",
      "comments": [],
      "estimated_hours": null,
      "task_type": "milestone",
      "created_at": "2026-02-14T05:23:30.018146+00:00",
      "updated_at": "2026-02-14T05:23:30.018146+00:00",
      "dependencies": [],
      "include_weekends": false
    },
    {
      "id": "1771046571829-1771046587385",
      "project_id": 1771046571829,
      "name": "Ray 実装 3/4",
      "phase": "wire",
      "assignee": "nishitani",
      "start_date": "2026-02-16",
      "end_date": "2026-02-20",
      "done": false,
      "task_status": "inbox",
      "description": "",
      "comments": [],
      "estimated_hours": null,
      "task_type": null,
      "created_at": "2026-02-14T05:23:09.363228+00:00",
      "updated_at": "2026-02-14T05:23:09.363228+00:00",
      "dependencies": [],
      "include_weekends": false
    },
    {
      "id": "1771046571829-1771046669540",
      "project_id": 1771046571829,
      "name": "Ray 調整対応",
      "phase": "wire",
      "assignee": "nishitani",
      "start_date": "2026-03-09",
      "end_date": "2026-03-13",
      "done": false,
      "task_status": "inbox",
      "description": "",
      "comments": [],
      "estimated_hours": null,
      "task_type": null,
      "created_at": "2026-02-14T05:24:31.726869+00:00",
      "updated_at": "2026-02-14T05:24:31.726869+00:00",
      "dependencies": [],
      "include_weekends": false
    },
    {
      "id": "1771046571829-1771046681594",
      "project_id": 1771046571829,
      "name": "Ray 公開",
      "phase": "wire",
      "assignee": "nishitani",
      "start_date": "2026-03-20",
      "end_date": "2026-03-20",
      "done": false,
      "task_status": "inbox",
      "description": "",
      "comments": [],
      "estimated_hours": null,
      "task_type": "milestone",
      "created_at": "2026-02-14T05:24:43.58454+00:00",
      "updated_at": "2026-02-14T05:24:43.58454+00:00",
      "dependencies": [],
      "include_weekends": false
    },
    {
      "id": "1771045915922-0",
      "project_id": 1771045915922,
      "name": "両備ホームズ採用パンフレット 全体デザイン作成",
      "phase": "design",
      "assignee": "fujii",
      "start_date": "2026-02-23",
      "end_date": "2026-02-25",
      "done": false,
      "task_status": "todo",
      "description": "",
      "comments": [],
      "estimated_hours": null,
      "task_type": null,
      "created_at": "2026-02-14T05:11:58.956749+00:00",
      "updated_at": "2026-02-14T05:11:58.956749+00:00",
      "dependencies": [],
      "include_weekends": false
    },
    {
      "id": "1771045915922-1",
      "project_id": 1771045915922,
      "name": "両備ホームズ採用パンフレット デザイン提出",
      "phase": "design",
      "assignee": "fujii",
      "start_date": "2026-03-04",
      "end_date": "2026-03-04",
      "done": false,
      "task_status": "todo",
      "description": "",
      "comments": [],
      "estimated_hours": null,
      "task_type": "milestone",
      "created_at": "2026-02-14T05:11:58.956749+00:00",
      "updated_at": "2026-02-14T05:11:58.956749+00:00",
      "dependencies": [],
      "include_weekends": false
    },
    {
      "id": "1771045915922-2",
      "project_id": 1771045915922,
      "name": "両備ホームズ採用パンフレット デザイン修正指示",
      "phase": "design",
      "assignee": "client",
      "start_date": "2026-03-06",
      "end_date": "2026-03-06",
      "done": false,
      "task_status": "todo",
      "description": "",
      "comments": [],
      "estimated_hours": null,
      "task_type": "milestone",
      "created_at": "2026-02-14T05:11:58.956749+00:00",
      "updated_at": "2026-02-14T05:11:58.956749+00:00",
      "dependencies": [],
      "include_weekends": false
    },
    {
      "id": "1771045915922-3",
      "project_id": 1771045915922,
      "name": "両備ホームズ採用パンフレット 最終調整",
      "phase": "design",
      "assignee": "fujii",
      "start_date": "2026-03-09",
      "end_date": "2026-03-11",
      "done": false,
      "task_status": "todo",
      "description": "",
      "comments": [],
      "estimated_hours": null,
      "task_type": null,
      "created_at": "2026-02-14T05:11:58.956749+00:00",
      "updated_at": "2026-02-14T05:11:58.956749+00:00",
      "dependencies": [],
      "include_weekends": false
    },
    {
      "id": "1771045915922-4",
      "project_id": 1771045915922,
      "name": "両備ホームズ採用パンフレット 最終確認",
      "phase": "design",
      "assignee": "fujii",
      "start_date": "2026-03-13",
      "end_date": "2026-03-13",
      "done": false,
      "task_status": "todo",
      "description": "",
      "comments": [],
      "estimated_hours": null,
      "task_type": "milestone",
      "created_at": "2026-02-14T05:11:58.956749+00:00",
      "updated_at": "2026-02-14T05:11:58.956749+00:00",
      "dependencies": [],
      "include_weekends": false
    },
    {
      "id": "1771044296039-13",
      "project_id": 1771044296039,
      "name": "グリッジ採用LP コーディング",
      "phase": "design",
      "assignee": "nishitani",
      "start_date": "2026-05-04",
      "end_date": "2026-05-08",
      "done": false,
      "task_status": "todo",
      "description": "",
      "comments": [],
      "estimated_hours": null,
      "task_type": null,
      "created_at": "2026-02-14T04:44:57.863188+00:00",
      "updated_at": "2026-02-14T04:44:57.863188+00:00",
      "dependencies": [],
      "include_weekends": false
    },
    {
      "id": "1771044296039-14",
      "project_id": 1771044296039,
      "name": "グリッジ採用LP デモサイト社内提出",
      "phase": "design",
      "assignee": "nishitani",
      "start_date": "2026-05-11",
      "end_date": "2026-05-11",
      "done": false,
      "task_status": "todo",
      "description": "",
      "comments": [],
      "estimated_hours": null,
      "task_type": "milestone",
      "created_at": "2026-02-14T04:44:57.863188+00:00",
      "updated_at": "2026-02-14T04:44:57.863188+00:00",
      "dependencies": [],
      "include_weekends": false
    },
    {
      "id": "1771048409595-5",
      "project_id": 1771048223028,
      "name": "萩原（HP・採用） デモサイト最終修正",
      "phase": "design",
      "assignee": "nishitani",
      "start_date": "2026-06-29",
      "end_date": "2026-07-03",
      "done": false,
      "task_status": "todo",
      "description": "",
      "comments": [],
      "estimated_hours": null,
      "task_type": null,
      "created_at": "2026-02-14T05:53:31.484455+00:00",
      "updated_at": "2026-02-14T05:53:31.484455+00:00",
      "dependencies": [],
      "include_weekends": false
    },
    {
      "id": "1771048223028-4",
      "project_id": 1771048223028,
      "name": "萩原（HP・採用） WF確認",
      "phase": "design",
      "assignee": "client",
      "start_date": "2026-02-27",
      "end_date": "2026-02-27",
      "done": false,
      "task_status": "todo",
      "description": "",
      "comments": [],
      "estimated_hours": null,
      "task_type": "milestone",
      "created_at": "2026-02-14T05:50:25.052033+00:00",
      "updated_at": "2026-02-14T05:50:25.052033+00:00",
      "dependencies": [],
      "include_weekends": false
    },
    {
      "id": "1771048223028-5",
      "project_id": 1771048223028,
      "name": "萩原（HP・採用） 初稿デザイン提出",
      "phase": "design",
      "assignee": "fujii",
      "start_date": "2026-03-16",
      "end_date": "2026-03-16",
      "done": false,
      "task_status": "todo",
      "description": "",
      "comments": [],
      "estimated_hours": null,
      "task_type": "milestone",
      "created_at": "2026-02-14T05:50:25.052033+00:00",
      "updated_at": "2026-02-14T05:50:25.052033+00:00",
      "dependencies": [],
      "include_weekends": false
    },
    {
      "id": "1771048223028-9",
      "project_id": 1771048223028,
      "name": "萩原（HP・採用） 全体ページデザイン 2/2",
      "phase": "design",
      "assignee": "fujii",
      "start_date": "2026-04-13",
      "end_date": "2026-04-17",
      "done": false,
      "task_status": "todo",
      "description": "",
      "comments": [],
      "estimated_hours": null,
      "task_type": null,
      "created_at": "2026-02-14T05:50:25.052033+00:00",
      "updated_at": "2026-02-14T05:50:25.052033+00:00",
      "dependencies": [],
      "include_weekends": false
    },
    {
      "id": "1771048223028-11",
      "project_id": 1771048223028,
      "name": "萩原（HP・採用） 全体デザイン提出",
      "phase": "design",
      "assignee": "fujii",
      "start_date": "2026-04-29",
      "end_date": "2026-04-29",
      "done": false,
      "task_status": "todo",
      "description": "",
      "comments": [],
      "estimated_hours": null,
      "task_type": "milestone",
      "created_at": "2026-02-14T05:50:25.052033+00:00",
      "updated_at": "2026-02-14T05:50:25.052033+00:00",
      "dependencies": [],
      "include_weekends": false
    },
    {
      "id": "1771048223028-1771048305492",
      "project_id": 1771048223028,
      "name": "萩原下層WF作成",
      "phase": "wire",
      "assignee": "imashige",
      "start_date": "2026-03-02",
      "end_date": "2026-03-06",
      "done": false,
      "task_status": "inbox",
      "description": "",
      "comments": [],
      "estimated_hours": null,
      "task_type": null,
      "created_at": "2026-02-14T05:51:47.904595+00:00",
      "updated_at": "2026-02-14T05:51:47.904595+00:00",
      "dependencies": [],
      "include_weekends": false
    },
    {
      "id": "1771048146478-6",
      "project_id": 1771048146478,
      "name": "高野工業 デモサイト提出",
      "phase": "design",
      "assignee": "nishitani",
      "start_date": "2026-03-13",
      "end_date": "2026-03-13",
      "done": false,
      "task_status": "todo",
      "description": "",
      "comments": [],
      "estimated_hours": null,
      "task_type": "milestone",
      "created_at": "2026-02-14T05:49:08.805624+00:00",
      "updated_at": "2026-02-14T05:49:08.805624+00:00",
      "dependencies": [],
      "include_weekends": false
    },
    {
      "id": "1771048146478-7",
      "project_id": 1771048146478,
      "name": "高野工業 デモサイト最終修正",
      "phase": "design",
      "assignee": "nishitani",
      "start_date": "2026-03-20",
      "end_date": "2026-03-20",
      "done": false,
      "task_status": "todo",
      "description": "",
      "comments": [],
      "estimated_hours": null,
      "task_type": "milestone",
      "created_at": "2026-02-14T05:49:08.805624+00:00",
      "updated_at": "2026-02-14T05:49:08.805624+00:00",
      "dependencies": [],
      "include_weekends": false
    },
    {
      "id": "1771048146478-8",
      "project_id": 1771048146478,
      "name": "高野工業 公開",
      "phase": "design",
      "assignee": "nishitani",
      "start_date": "2026-03-27",
      "end_date": "2026-03-27",
      "done": false,
      "task_status": "todo",
      "description": "",
      "comments": [],
      "estimated_hours": null,
      "task_type": "milestone",
      "created_at": "2026-02-14T05:49:08.805624+00:00",
      "updated_at": "2026-02-14T05:49:08.805624+00:00",
      "dependencies": [],
      "include_weekends": false
    },
    {
      "id": "1771047702705-0",
      "project_id": 1771047702705,
      "name": "アクティブアスベスト コーディング 2/3",
      "phase": "design",
      "assignee": "member_1771048904241",
      "start_date": "2026-02-16",
      "end_date": "2026-02-27",
      "done": false,
      "task_status": "todo",
      "description": "",
      "comments": [],
      "estimated_hours": null,
      "task_type": null,
      "created_at": "2026-02-14T05:41:45.377527+00:00",
      "updated_at": "2026-02-14T05:41:45.377527+00:00",
      "dependencies": [],
      "include_weekends": false
    },
    {
      "id": "1771047702705-1",
      "project_id": 1771047702705,
      "name": "アクティブアスベスト調整〆切（船井総研）",
      "phase": "design",
      "assignee": "client",
      "start_date": "2026-02-18",
      "end_date": "2026-02-18",
      "done": false,
      "task_status": "todo",
      "description": "",
      "comments": [],
      "estimated_hours": null,
      "task_type": "milestone",
      "created_at": "2026-02-14T05:41:45.377527+00:00",
      "updated_at": "2026-02-14T05:41:45.377527+00:00",
      "dependencies": [],
      "include_weekends": false
    },
    {
      "id": "1771047702705-3",
      "project_id": 1771047702705,
      "name": "アクティブアスベスト デモサイト社内提出",
      "phase": "design",
      "assignee": "member_1771048904241",
      "start_date": "2026-02-25",
      "end_date": "2026-02-25",
      "done": false,
      "task_status": "todo",
      "description": "",
      "comments": [],
      "estimated_hours": null,
      "task_type": "milestone",
      "created_at": "2026-02-14T05:41:45.377527+00:00",
      "updated_at": "2026-02-14T05:41:45.377527+00:00",
      "dependencies": [],
      "include_weekends": false
    },
    {
      "id": "1771047702705-4",
      "project_id": 1771047702705,
      "name": "アクティブアスベスト デモサイト提出",
      "phase": "design",
      "assignee": "nishitani",
      "start_date": "2026-02-27",
      "end_date": "2026-02-27",
      "done": false,
      "task_status": "todo",
      "description": "",
      "comments": [],
      "estimated_hours": null,
      "task_type": "milestone",
      "created_at": "2026-02-14T05:41:45.377527+00:00",
      "updated_at": "2026-02-14T05:41:45.377527+00:00",
      "dependencies": [],
      "include_weekends": false
    },
    {
      "id": "1771047215241-1",
      "project_id": 1771047215241,
      "name": "両備HM風の野LP 全体デザイン提出",
      "phase": "design",
      "assignee": "fujii",
      "start_date": "2026-02-13",
      "end_date": "2026-02-13",
      "done": false,
      "task_status": "todo",
      "description": "",
      "comments": [],
      "estimated_hours": null,
      "task_type": "milestone",
      "created_at": "2026-02-14T05:33:37.260611+00:00",
      "updated_at": "2026-02-14T05:33:37.260611+00:00",
      "dependencies": [],
      "include_weekends": false
    },
    {
      "id": "1771047215241-2",
      "project_id": 1771047215241,
      "name": "両備HM風の野LP 全体デザイン提出",
      "phase": "design",
      "assignee": "fujii",
      "start_date": "2026-02-16",
      "end_date": "2026-02-16",
      "done": false,
      "task_status": "todo",
      "description": "",
      "comments": [],
      "estimated_hours": null,
      "task_type": "milestone",
      "created_at": "2026-02-14T05:33:37.260611+00:00",
      "updated_at": "2026-02-14T05:33:37.260611+00:00",
      "dependencies": [],
      "include_weekends": false
    },
    {
      "id": "1771047215241-3",
      "project_id": 1771047215241,
      "name": "両備HM風の野LP 全体デザイン修正指示",
      "phase": "design",
      "assignee": "client",
      "start_date": "2026-02-20",
      "end_date": "2026-02-20",
      "done": false,
      "task_status": "todo",
      "description": "",
      "comments": [],
      "estimated_hours": null,
      "task_type": "milestone",
      "created_at": "2026-02-14T05:33:37.260611+00:00",
      "updated_at": "2026-02-14T05:33:37.260611+00:00",
      "dependencies": [],
      "include_weekends": false
    },
    {
      "id": "1771047215241-4",
      "project_id": 1771047215241,
      "name": "両備HM風の野LP コーディング 1/2",
      "phase": "design",
      "assignee": "nishitani",
      "start_date": "2026-02-23",
      "end_date": "2026-02-27",
      "done": false,
      "task_status": "todo",
      "description": "",
      "comments": [],
      "estimated_hours": null,
      "task_type": null,
      "created_at": "2026-02-14T05:33:37.260611+00:00",
      "updated_at": "2026-02-14T05:33:37.260611+00:00",
      "dependencies": [],
      "include_weekends": false
    },
    {
      "id": "1771047215241-5",
      "project_id": 1771047215241,
      "name": "両備HM風の野LP コーディング 2/2",
      "phase": "design",
      "assignee": "nishitani",
      "start_date": "2026-03-02",
      "end_date": "2026-03-06",
      "done": false,
      "task_status": "todo",
      "description": "",
      "comments": [],
      "estimated_hours": null,
      "task_type": null,
      "created_at": "2026-02-14T05:33:37.260611+00:00",
      "updated_at": "2026-02-14T05:33:37.260611+00:00",
      "dependencies": [],
      "include_weekends": false
    },
    {
      "id": "1771046938995-9",
      "project_id": 1771046938995,
      "name": "重藤組HP 全体ページデザイン（花菜） 2/2",
      "phase": "design",
      "assignee": "member_1771048866898",
      "start_date": "2026-03-30",
      "end_date": "2026-04-03",
      "done": false,
      "task_status": "todo",
      "description": "",
      "comments": [],
      "estimated_hours": null,
      "task_type": null,
      "created_at": "2026-02-14T05:29:01.014397+00:00",
      "updated_at": "2026-02-14T05:29:01.014397+00:00",
      "dependencies": [],
      "include_weekends": false
    },
    {
      "id": "1771046938995-10",
      "project_id": 1771046938995,
      "name": "重藤組HP 全体ページデザイン",
      "phase": "design",
      "assignee": "member_1771048866898",
      "start_date": "2026-03-23",
      "end_date": "2026-03-27",
      "done": false,
      "task_status": "todo",
      "description": "",
      "comments": [],
      "estimated_hours": null,
      "task_type": null,
      "created_at": "2026-02-14T05:29:01.014397+00:00",
      "updated_at": "2026-02-14T05:29:01.014397+00:00",
      "dependencies": [],
      "include_weekends": false
    },
    {
      "id": "1771046938995-11",
      "project_id": 1771046938995,
      "name": "重藤組HP 全体デザイン提出",
      "phase": "design",
      "assignee": "imashige",
      "start_date": "2026-04-10",
      "end_date": "2026-04-10",
      "done": false,
      "task_status": "todo",
      "description": "",
      "comments": [],
      "estimated_hours": null,
      "task_type": "milestone",
      "created_at": "2026-02-14T05:29:01.014397+00:00",
      "updated_at": "2026-02-14T05:29:01.014397+00:00",
      "dependencies": [],
      "include_weekends": false
    },
    {
      "id": "1771043105398-1771061175356",
      "project_id": 1771044832283,
      "name": "oneunity2パンフレット デザイン作成",
      "phase": "wire",
      "assignee": "member_1771061146147",
      "start_date": "2026-02-23",
      "end_date": "2026-02-27",
      "done": false,
      "task_status": "inbox",
      "description": "",
      "comments": [],
      "estimated_hours": null,
      "task_type": null,
      "created_at": "2026-02-14T09:26:18.006533+00:00",
      "updated_at": "2026-02-14T09:26:18.006533+00:00",
      "dependencies": [],
      "include_weekends": false
    },
    {
      "id": "1771048223028-10",
      "project_id": 1771048223028,
      "name": "萩原（HP・採用） 全体デザイン提出",
      "phase": "design",
      "assignee": "fujii",
      "start_date": "2026-05-01",
      "end_date": "2026-05-01",
      "done": false,
      "task_status": "todo",
      "description": "",
      "comments": [],
      "estimated_hours": null,
      "task_type": "milestone",
      "created_at": "2026-02-14T05:50:25.052033+00:00",
      "updated_at": "2026-02-14T05:50:25.052033+00:00",
      "dependencies": [],
      "include_weekends": false
    },
    {
      "id": "1771043349669-1771043356638",
      "project_id": 1771048223028,
      "name": "萩原（HP・採用） トップページデザイン",
      "phase": "wire",
      "assignee": "fujii",
      "start_date": "2026-03-02",
      "end_date": "2026-03-06",
      "done": false,
      "task_status": "inbox",
      "description": "",
      "comments": [],
      "estimated_hours": null,
      "task_type": null,
      "created_at": "2026-02-14T04:29:19.192648+00:00",
      "updated_at": "2026-02-14T04:29:19.192648+00:00",
      "dependencies": [],
      "include_weekends": false
    },
    {
      "id": "1771047215241-8",
      "project_id": 1771047215241,
      "name": "両備HM風の野LP デモサイト最終修正",
      "phase": "design",
      "assignee": "client",
      "start_date": "2026-03-16",
      "end_date": "2026-03-16",
      "done": false,
      "task_status": "todo",
      "description": "",
      "comments": [],
      "estimated_hours": null,
      "task_type": "milestone",
      "created_at": "2026-02-14T05:33:37.260611+00:00",
      "updated_at": "2026-02-14T05:33:37.260611+00:00",
      "dependencies": [],
      "include_weekends": false
    },
    {
      "id": "1771047215241-9",
      "project_id": 1771047215241,
      "name": "両備HM風の野LP デモサイト最終修正",
      "phase": "design",
      "assignee": "nishitani",
      "start_date": "2026-03-18",
      "end_date": "2026-03-19",
      "done": false,
      "task_status": "todo",
      "description": "",
      "comments": [],
      "estimated_hours": null,
      "task_type": null,
      "created_at": "2026-02-14T05:33:37.260611+00:00",
      "updated_at": "2026-02-14T05:33:37.260611+00:00",
      "dependencies": [],
      "include_weekends": false
    },
    {
      "id": "1771047215241-10",
      "project_id": 1771047215241,
      "name": "両備HM風の野LP 公開",
      "phase": "design",
      "assignee": "nishitani",
      "start_date": "2026-03-20",
      "end_date": "2026-03-20",
      "done": false,
      "task_status": "todo",
      "description": "",
      "comments": [],
      "estimated_hours": null,
      "task_type": "milestone",
      "created_at": "2026-02-14T05:33:37.260611+00:00",
      "updated_at": "2026-02-14T05:33:37.260611+00:00",
      "dependencies": [],
      "include_weekends": false
    },
    {
      "id": "1771047136752-1",
      "project_id": 1771047136752,
      "name": "三宅医院 デザイン提出",
      "phase": "design",
      "assignee": "member_1771048866898",
      "start_date": "2026-02-18",
      "end_date": "2026-02-18",
      "done": false,
      "task_status": "todo",
      "description": "",
      "comments": [],
      "estimated_hours": null,
      "task_type": "milestone",
      "created_at": "2026-02-14T05:32:19.184922+00:00",
      "updated_at": "2026-02-14T05:32:19.184922+00:00",
      "dependencies": [],
      "include_weekends": false
    },
    {
      "id": "1771047136752-2",
      "project_id": 1771047136752,
      "name": "三宅医院 デザイン提出",
      "phase": "design",
      "assignee": "shimizu",
      "start_date": "2026-02-20",
      "end_date": "2026-02-20",
      "done": false,
      "task_status": "todo",
      "description": "",
      "comments": [],
      "estimated_hours": null,
      "task_type": "milestone",
      "created_at": "2026-02-14T05:32:19.184922+00:00",
      "updated_at": "2026-02-14T05:32:19.184922+00:00",
      "dependencies": [],
      "include_weekends": false
    },
    {
      "id": "1771046938995-12",
      "project_id": 1771046938995,
      "name": "重藤組HP 全体デザイン提出",
      "phase": "design",
      "assignee": "member_1771048866898",
      "start_date": "2026-04-06",
      "end_date": "2026-04-06",
      "done": false,
      "task_status": "todo",
      "description": "",
      "comments": [],
      "estimated_hours": null,
      "task_type": "milestone",
      "created_at": "2026-02-14T05:29:01.014397+00:00",
      "updated_at": "2026-02-14T05:29:01.014397+00:00",
      "dependencies": [],
      "include_weekends": false
    },
    {
      "id": "1771046938995-13",
      "project_id": 1771046938995,
      "name": "重藤組HP ライター原稿提出・写真提出",
      "phase": "design",
      "assignee": "imashige",
      "start_date": "2026-04-17",
      "end_date": "2026-04-17",
      "done": false,
      "task_status": "todo",
      "description": "",
      "comments": [],
      "estimated_hours": null,
      "task_type": "milestone",
      "created_at": "2026-02-14T05:29:01.014397+00:00",
      "updated_at": "2026-02-14T05:29:01.014397+00:00",
      "dependencies": [],
      "include_weekends": false
    },
    {
      "id": "1771046938995-15",
      "project_id": 1771046938995,
      "name": "重藤組HP コーディング 2/2",
      "phase": "design",
      "assignee": "nishitani",
      "start_date": "2026-04-27",
      "end_date": "2026-05-01",
      "done": false,
      "task_status": "todo",
      "description": "",
      "comments": [],
      "estimated_hours": null,
      "task_type": null,
      "created_at": "2026-02-14T05:29:01.014397+00:00",
      "updated_at": "2026-02-14T05:29:01.014397+00:00",
      "dependencies": [],
      "include_weekends": false
    },
    {
      "id": "1771046938995-17",
      "project_id": 1771046938995,
      "name": "重藤組HP デモサイト社内提出",
      "phase": "design",
      "assignee": "nishitani",
      "start_date": "2026-05-11",
      "end_date": "2026-05-11",
      "done": false,
      "task_status": "todo",
      "description": "",
      "comments": [],
      "estimated_hours": null,
      "task_type": "milestone",
      "created_at": "2026-02-14T05:29:01.014397+00:00",
      "updated_at": "2026-02-14T05:29:01.014397+00:00",
      "dependencies": [],
      "include_weekends": false
    },
    {
      "id": "1771046938995-0",
      "project_id": 1771046938995,
      "name": "重藤組HP WF作成トップ",
      "phase": "design",
      "assignee": "imashige",
      "start_date": "2026-02-16",
      "end_date": "2026-02-18",
      "done": false,
      "task_status": "todo",
      "description": "",
      "comments": [],
      "estimated_hours": null,
      "task_type": null,
      "created_at": "2026-02-14T05:29:01.014397+00:00",
      "updated_at": "2026-02-14T05:29:01.014397+00:00",
      "dependencies": [],
      "include_weekends": false
    },
    {
      "id": "1771046938995-1",
      "project_id": 1771046938995,
      "name": "重藤組HP WF提出",
      "phase": "design",
      "assignee": "imashige",
      "start_date": "2026-02-20",
      "end_date": "2026-02-20",
      "done": false,
      "task_status": "todo",
      "description": "",
      "comments": [],
      "estimated_hours": null,
      "task_type": "milestone",
      "created_at": "2026-02-14T05:29:01.014397+00:00",
      "updated_at": "2026-02-14T05:29:01.014397+00:00",
      "dependencies": [],
      "include_weekends": false
    },
    {
      "id": "1771046938995-2",
      "project_id": 1771046938995,
      "name": "重藤組HP トップページ",
      "phase": "design",
      "assignee": "member_1771048895950",
      "start_date": "2026-02-23",
      "end_date": "2026-02-27",
      "done": false,
      "task_status": "todo",
      "description": "",
      "comments": [],
      "estimated_hours": null,
      "task_type": null,
      "created_at": "2026-02-14T05:29:01.014397+00:00",
      "updated_at": "2026-02-14T05:29:01.014397+00:00",
      "dependencies": [],
      "include_weekends": false
    },
    {
      "id": "1771046938995-3",
      "project_id": 1771046938995,
      "name": "重藤組HP 初稿デザイン提出",
      "phase": "design",
      "assignee": "imashige",
      "start_date": "2026-03-02",
      "end_date": "2026-03-02",
      "done": false,
      "task_status": "todo",
      "description": "",
      "comments": [],
      "estimated_hours": null,
      "task_type": "milestone",
      "created_at": "2026-02-14T05:29:01.014397+00:00",
      "updated_at": "2026-02-14T05:29:01.014397+00:00",
      "dependencies": [],
      "include_weekends": false
    },
    {
      "id": "1771046938995-4",
      "project_id": 1771046938995,
      "name": "重藤組HP 初稿デザイン提出",
      "phase": "design",
      "assignee": "imashige",
      "start_date": "2026-03-06",
      "end_date": "2026-03-06",
      "done": false,
      "task_status": "todo",
      "description": "",
      "comments": [],
      "estimated_hours": null,
      "task_type": "milestone",
      "created_at": "2026-02-14T05:29:01.014397+00:00",
      "updated_at": "2026-02-14T05:29:01.014397+00:00",
      "dependencies": [],
      "include_weekends": false
    },
    {
      "id": "1771046938995-5",
      "project_id": 1771046938995,
      "name": "重藤組HP ライター手配・写真手配",
      "phase": "design",
      "assignee": "imashige",
      "start_date": "2026-03-13",
      "end_date": "2026-03-13",
      "done": false,
      "task_status": "todo",
      "description": "",
      "comments": [],
      "estimated_hours": null,
      "task_type": "milestone",
      "created_at": "2026-02-14T05:29:01.014397+00:00",
      "updated_at": "2026-02-14T05:29:01.014397+00:00",
      "dependencies": [],
      "include_weekends": false
    },
    {
      "id": "1771046938995-6",
      "project_id": 1771046938995,
      "name": "(〆重藤組HP 初稿デザイン修正指示）",
      "phase": "design",
      "assignee": "client",
      "start_date": "2026-03-13",
      "end_date": "2026-03-13",
      "done": false,
      "task_status": "todo",
      "description": "",
      "comments": [],
      "estimated_hours": null,
      "task_type": "milestone",
      "created_at": "2026-02-14T05:29:01.014397+00:00",
      "updated_at": "2026-02-14T05:29:01.014397+00:00",
      "dependencies": [],
      "include_weekends": false
    },
    {
      "id": "1771046938995-7",
      "project_id": 1771046938995,
      "name": "重藤組HP 下層WF作成",
      "phase": "design",
      "assignee": "imashige",
      "start_date": "2026-03-16",
      "end_date": "2026-03-20",
      "done": false,
      "task_status": "todo",
      "description": "",
      "comments": [],
      "estimated_hours": null,
      "task_type": null,
      "created_at": "2026-02-14T05:29:01.014397+00:00",
      "updated_at": "2026-02-14T05:29:01.014397+00:00",
      "dependencies": [],
      "include_weekends": false
    },
    {
      "id": "1771046938995-8",
      "project_id": 1771046938995,
      "name": "重藤組HP ライティング",
      "phase": "design",
      "assignee": "member_1771054314937",
      "start_date": "2026-03-23",
      "end_date": "2026-03-27",
      "done": false,
      "task_status": "todo",
      "description": "",
      "comments": [],
      "estimated_hours": null,
      "task_type": null,
      "created_at": "2026-02-14T05:29:01.014397+00:00",
      "updated_at": "2026-02-14T05:29:01.014397+00:00",
      "dependencies": [],
      "include_weekends": false
    },
    {
      "id": "1771044832283-0",
      "project_id": 1771044832283,
      "name": "oneunity2パンフレット 構成作成",
      "phase": "design",
      "assignee": "fujii",
      "start_date": "2026-02-16",
      "end_date": "2026-02-17",
      "done": false,
      "task_status": "todo",
      "description": "",
      "comments": [],
      "estimated_hours": null,
      "task_type": null,
      "created_at": "2026-02-14T04:53:54.431497+00:00",
      "updated_at": "2026-02-14T04:53:54.431497+00:00",
      "dependencies": [],
      "include_weekends": false
    },
    {
      "id": "1771044832283-1",
      "project_id": 1771044832283,
      "name": "oneunity2パンフレット デザイン提出",
      "phase": "design",
      "assignee": "member_1771061146147",
      "start_date": "2026-03-04",
      "end_date": "2026-03-04",
      "done": false,
      "task_status": "todo",
      "description": "",
      "comments": [],
      "estimated_hours": null,
      "task_type": "milestone",
      "created_at": "2026-02-14T04:53:54.431497+00:00",
      "updated_at": "2026-02-14T04:53:54.431497+00:00",
      "dependencies": [],
      "include_weekends": false
    },
    {
      "id": "1771048223028-12",
      "project_id": 1771048223028,
      "name": "萩原（HP・採用） 全体デザイン修正指示",
      "phase": "design",
      "assignee": "client",
      "start_date": "2026-05-15",
      "end_date": "2026-05-15",
      "done": false,
      "task_status": "todo",
      "description": "",
      "comments": [],
      "estimated_hours": null,
      "task_type": "milestone",
      "created_at": "2026-02-14T05:50:25.052033+00:00",
      "updated_at": "2026-02-14T05:50:25.052033+00:00",
      "dependencies": [],
      "include_weekends": false
    },
    {
      "id": "1771048223028-13",
      "project_id": 1771048223028,
      "name": "萩原（HP・採用） 公開",
      "phase": "design",
      "assignee": "nishitani",
      "start_date": "2026-07-17",
      "end_date": "2026-07-17",
      "done": false,
      "task_status": "todo",
      "description": "",
      "comments": [],
      "estimated_hours": null,
      "task_type": "milestone",
      "created_at": "2026-02-14T05:50:25.052033+00:00",
      "updated_at": "2026-02-14T05:50:25.052033+00:00",
      "dependencies": [],
      "include_weekends": false
    },
    {
      "id": "1771048146478-0",
      "project_id": 1771048146478,
      "name": "高野工業 ライター原稿提出・写真提出",
      "phase": "design",
      "assignee": "imashige",
      "start_date": "2026-02-20",
      "end_date": "2026-02-20",
      "done": false,
      "task_status": "todo",
      "description": "",
      "comments": [],
      "estimated_hours": null,
      "task_type": "milestone",
      "created_at": "2026-02-14T05:49:08.805624+00:00",
      "updated_at": "2026-02-14T05:49:08.805624+00:00",
      "dependencies": [],
      "include_weekends": false
    },
    {
      "id": "1771048146478-1",
      "project_id": 1771048146478,
      "name": "高野工業 全体デザイン修正指示",
      "phase": "design",
      "assignee": "client",
      "start_date": "2026-02-20",
      "end_date": "2026-02-20",
      "done": false,
      "task_status": "todo",
      "description": "",
      "comments": [],
      "estimated_hours": null,
      "task_type": "milestone",
      "created_at": "2026-02-14T05:49:08.805624+00:00",
      "updated_at": "2026-02-14T05:49:08.805624+00:00",
      "dependencies": [],
      "include_weekends": false
    },
    {
      "id": "1771048146478-2",
      "project_id": 1771048146478,
      "name": "高野工業ライティング",
      "phase": "design",
      "assignee": "imashige",
      "start_date": "2026-02-24",
      "end_date": "2026-02-27",
      "done": false,
      "task_status": "todo",
      "description": "",
      "comments": [],
      "estimated_hours": null,
      "task_type": null,
      "created_at": "2026-02-14T05:49:08.805624+00:00",
      "updated_at": "2026-02-14T05:49:08.805624+00:00",
      "dependencies": [],
      "include_weekends": false
    },
    {
      "id": "1771048146478-3",
      "project_id": 1771048146478,
      "name": "高野工業 コーディング 1/2",
      "phase": "design",
      "assignee": "member_1771048904241",
      "start_date": "2026-03-02",
      "end_date": "2026-03-06",
      "done": false,
      "task_status": "todo",
      "description": "",
      "comments": [],
      "estimated_hours": null,
      "task_type": null,
      "created_at": "2026-02-14T05:49:08.805624+00:00",
      "updated_at": "2026-02-14T05:49:08.805624+00:00",
      "dependencies": [],
      "include_weekends": false
    },
    {
      "id": "1771048146478-4",
      "project_id": 1771048146478,
      "name": "高野工業 コーディング 2/2",
      "phase": "design",
      "assignee": "member_1771048904241",
      "start_date": "2026-03-09",
      "end_date": "2026-03-13",
      "done": false,
      "task_status": "todo",
      "description": "",
      "comments": [],
      "estimated_hours": null,
      "task_type": null,
      "created_at": "2026-02-14T05:49:08.805624+00:00",
      "updated_at": "2026-02-14T05:49:08.805624+00:00",
      "dependencies": [],
      "include_weekends": false
    },
    {
      "id": "1771048146478-5",
      "project_id": 1771048146478,
      "name": "高野工業 デモサイト社内提出",
      "phase": "design",
      "assignee": "member_1771048904241",
      "start_date": "2026-03-11",
      "end_date": "2026-03-11",
      "done": false,
      "task_status": "todo",
      "description": "",
      "comments": [],
      "estimated_hours": null,
      "task_type": "milestone",
      "created_at": "2026-02-14T05:49:08.805624+00:00",
      "updated_at": "2026-02-14T05:49:08.805624+00:00",
      "dependencies": [],
      "include_weekends": false
    },
    {
      "id": "1771047174687-7",
      "project_id": 1771047174687,
      "name": "両備HM津島福居LP コーディング",
      "phase": "design",
      "assignee": "nishitani",
      "start_date": "2026-03-16",
      "end_date": "2026-03-20",
      "done": false,
      "task_status": "todo",
      "description": "",
      "comments": [],
      "estimated_hours": null,
      "task_type": null,
      "created_at": "2026-02-14T05:32:56.819472+00:00",
      "updated_at": "2026-02-14T05:32:56.819472+00:00",
      "dependencies": [],
      "include_weekends": false
    },
    {
      "id": "1771047174687-8",
      "project_id": 1771047174687,
      "name": "両備HM津島福居LP 全体デザイン修正指示",
      "phase": "design",
      "assignee": "client",
      "start_date": "2026-03-13",
      "end_date": "2026-03-13",
      "done": false,
      "task_status": "todo",
      "description": "",
      "comments": [],
      "estimated_hours": null,
      "task_type": "milestone",
      "created_at": "2026-02-14T05:32:56.819472+00:00",
      "updated_at": "2026-02-14T05:32:56.819472+00:00",
      "dependencies": [],
      "include_weekends": false
    },
    {
      "id": "1771046938995-16",
      "project_id": 1771046938995,
      "name": "重藤組HP コーディング 1/2",
      "phase": "design",
      "assignee": "nishitani",
      "start_date": "2026-04-20",
      "end_date": "2026-04-24",
      "done": false,
      "task_status": "todo",
      "description": "",
      "comments": [],
      "estimated_hours": null,
      "task_type": null,
      "created_at": "2026-02-14T05:29:01.014397+00:00",
      "updated_at": "2026-02-14T05:29:01.014397+00:00",
      "dependencies": [],
      "include_weekends": false
    },
    {
      "id": "1771044832283-11",
      "project_id": 1771044832283,
      "name": "oneunity2パンフレット 入稿",
      "phase": "design",
      "assignee": "fujii",
      "start_date": "2026-04-17",
      "end_date": "2026-04-17",
      "done": false,
      "task_status": "todo",
      "description": "",
      "comments": [],
      "estimated_hours": null,
      "task_type": "milestone",
      "created_at": "2026-02-14T04:53:54.431497+00:00",
      "updated_at": "2026-02-14T04:53:54.431497+00:00",
      "dependencies": [],
      "include_weekends": false
    },
    {
      "id": "1771044832283-2",
      "project_id": 1771044832283,
      "name": "oneunity2パンフレット デザイン提出",
      "phase": "design",
      "assignee": "fujii",
      "start_date": "2026-03-06",
      "end_date": "2026-03-06",
      "done": false,
      "task_status": "todo",
      "description": "",
      "comments": [],
      "estimated_hours": null,
      "task_type": "milestone",
      "created_at": "2026-02-14T04:53:54.431497+00:00",
      "updated_at": "2026-02-14T04:53:54.431497+00:00",
      "dependencies": [],
      "include_weekends": false
    },
    {
      "id": "1771044296039-15",
      "project_id": 1771044296039,
      "name": "グリッジ採用LP デモサイト提出",
      "phase": "design",
      "assignee": "nishitani",
      "start_date": "2026-05-15",
      "end_date": "2026-05-15",
      "done": false,
      "task_status": "todo",
      "description": "",
      "comments": [],
      "estimated_hours": null,
      "task_type": "milestone",
      "created_at": "2026-02-14T04:44:57.863188+00:00",
      "updated_at": "2026-02-14T04:44:57.863188+00:00",
      "dependencies": [],
      "include_weekends": false
    },
    {
      "id": "1771044296039-6",
      "project_id": 1771044296039,
      "name": "グリッジ採用LP ライター手配・写真手配",
      "phase": "design",
      "assignee": "shimizu",
      "start_date": "2026-03-27",
      "end_date": "2026-03-27",
      "done": false,
      "task_status": "todo",
      "description": "",
      "comments": [],
      "estimated_hours": null,
      "task_type": "milestone",
      "created_at": "2026-02-14T04:44:57.863188+00:00",
      "updated_at": "2026-02-14T04:44:57.863188+00:00",
      "dependencies": [],
      "include_weekends": false
    },
    {
      "id": "1771044296039-8",
      "project_id": 1771044296039,
      "name": "グリッジ採用LP 全体デザイン提出",
      "phase": "design",
      "assignee": "nakata",
      "start_date": "2026-04-13",
      "end_date": "2026-04-13",
      "done": false,
      "task_status": "todo",
      "description": "",
      "comments": [],
      "estimated_hours": null,
      "task_type": "milestone",
      "created_at": "2026-02-14T04:44:57.863188+00:00",
      "updated_at": "2026-02-14T04:44:57.863188+00:00",
      "dependencies": [],
      "include_weekends": false
    },
    {
      "id": "1771044296039-16",
      "project_id": 1771044296039,
      "name": "グリッジ採用LP 公開",
      "phase": "design",
      "assignee": "nishitani",
      "start_date": "2026-05-22",
      "end_date": "2026-05-22",
      "done": false,
      "task_status": "todo",
      "description": "",
      "comments": [],
      "estimated_hours": null,
      "task_type": "milestone",
      "created_at": "2026-02-14T04:44:57.863188+00:00",
      "updated_at": "2026-02-14T04:44:57.863188+00:00",
      "dependencies": [],
      "include_weekends": false
    },
    {
      "id": "1771044296039-5",
      "project_id": 1771044296039,
      "name": "(〆グリッジ採用LP 初稿デザイン修正指示）",
      "phase": "design",
      "assignee": "nakata",
      "start_date": "2026-03-27",
      "end_date": "2026-03-27",
      "done": false,
      "task_status": "todo",
      "description": "",
      "comments": [],
      "estimated_hours": null,
      "task_type": "milestone",
      "created_at": "2026-02-14T04:44:57.863188+00:00",
      "updated_at": "2026-02-14T04:44:57.863188+00:00",
      "dependencies": [],
      "include_weekends": false
    },
    {
      "id": "1771044296039-7",
      "project_id": 1771044296039,
      "name": "グリッジ採用LP 下層WF作成",
      "phase": "design",
      "assignee": "nakata",
      "start_date": "2026-03-30",
      "end_date": "2026-04-03",
      "done": false,
      "task_status": "todo",
      "description": "",
      "comments": [],
      "estimated_hours": null,
      "task_type": null,
      "created_at": "2026-02-14T04:44:57.863188+00:00",
      "updated_at": "2026-02-14T04:44:57.863188+00:00",
      "dependencies": [],
      "include_weekends": false
    },
    {
      "id": "1771044296039-0",
      "project_id": 1771044296039,
      "name": "グリッジ採用LP WF作成トップ",
      "phase": "design",
      "assignee": "nakata",
      "start_date": "2026-03-09",
      "end_date": "2026-03-10",
      "done": false,
      "task_status": "todo",
      "description": "",
      "comments": [],
      "estimated_hours": null,
      "task_type": null,
      "created_at": "2026-02-14T04:44:57.863188+00:00",
      "updated_at": "2026-02-14T04:44:57.863188+00:00",
      "dependencies": [],
      "include_weekends": false
    },
    {
      "id": "1771044296039-1",
      "project_id": 1771044296039,
      "name": "グリッジ採用LP WF提出",
      "phase": "design",
      "assignee": "nakata",
      "start_date": "2026-03-06",
      "end_date": "2026-03-06",
      "done": false,
      "task_status": "todo",
      "description": "",
      "comments": [],
      "estimated_hours": null,
      "task_type": "milestone",
      "created_at": "2026-02-14T04:44:57.863188+00:00",
      "updated_at": "2026-02-14T04:44:57.863188+00:00",
      "dependencies": [],
      "include_weekends": false
    },
    {
      "id": "1771044296039-4",
      "project_id": 1771044296039,
      "name": "グリッジ採用LP 初稿デザイン提出",
      "phase": "design",
      "assignee": "nakata",
      "start_date": "2026-03-23",
      "end_date": "2026-03-23",
      "done": false,
      "task_status": "todo",
      "description": "",
      "comments": [],
      "estimated_hours": null,
      "task_type": "milestone",
      "created_at": "2026-02-14T04:44:57.863188+00:00",
      "updated_at": "2026-02-14T04:44:57.863188+00:00",
      "dependencies": [],
      "include_weekends": false
    },
    {
      "id": "1771044296039-2",
      "project_id": 1771044296039,
      "name": "グリッジ採用LP トップページ",
      "phase": "design",
      "assignee": "nakata",
      "start_date": "2026-03-11",
      "end_date": "2026-03-13",
      "done": false,
      "task_status": "todo",
      "description": "",
      "comments": [],
      "estimated_hours": null,
      "task_type": null,
      "created_at": "2026-02-14T04:44:57.863188+00:00",
      "updated_at": "2026-02-14T04:44:57.863188+00:00",
      "dependencies": [],
      "include_weekends": false
    },
    {
      "id": "1771044296039-3",
      "project_id": 1771044296039,
      "name": "グリッジ採用LP 初稿デザイン提出",
      "phase": "design",
      "assignee": "nakata",
      "start_date": "2026-03-20",
      "end_date": "2026-03-20",
      "done": false,
      "task_status": "todo",
      "description": "",
      "comments": [],
      "estimated_hours": null,
      "task_type": "milestone",
      "created_at": "2026-02-14T04:44:57.863188+00:00",
      "updated_at": "2026-02-14T04:44:57.863188+00:00",
      "dependencies": [],
      "include_weekends": false
    },
    {
      "id": "t17710558695737sxcf",
      "project_id": 1771039129808,
      "name": "松浜・藤原西町2/4棟デザイン（バナー）残り",
      "phase": "wire",
      "assignee": "nakata",
      "start_date": "2026-02-24",
      "end_date": "2026-02-25",
      "done": false,
      "task_status": "inbox",
      "description": "",
      "comments": [],
      "estimated_hours": null,
      "task_type": null,
      "created_at": "2026-02-14T07:57:52.72025+00:00",
      "updated_at": "2026-02-14T07:57:52.72025+00:00",
      "dependencies": [],
      "include_weekends": false
    },
    {
      "id": "1771043105398-1771055966841",
      "project_id": 1771039129808,
      "name": "津島福居分譲地：企画構成",
      "phase": "wire",
      "assignee": null,
      "start_date": "2026-03-02",
      "end_date": "2026-03-02",
      "done": false,
      "task_status": "inbox",
      "description": "",
      "comments": [],
      "estimated_hours": null,
      "task_type": null,
      "created_at": "2026-02-14T07:59:29.470344+00:00",
      "updated_at": "2026-02-14T07:59:29.470344+00:00",
      "dependencies": [],
      "include_weekends": false
    },
    {
      "id": "1771039129808-1771041713915",
      "project_id": 1771039129808,
      "name": "両備ホームズ動画広告制作",
      "phase": "wire",
      "assignee": "honda",
      "start_date": "2026-02-16",
      "end_date": "2026-02-20",
      "done": false,
      "task_status": "inbox",
      "description": "",
      "comments": [],
      "estimated_hours": 10,
      "task_type": null,
      "created_at": "2026-02-14T04:02:00.485322+00:00",
      "updated_at": "2026-02-14T04:02:00.485322+00:00",
      "dependencies": [],
      "include_weekends": false
    },
    {
      "id": "t1771057220792ad9n3",
      "project_id": 1771039129808,
      "name": "津島福居分譲地：WF作成",
      "phase": "wire",
      "assignee": null,
      "start_date": "2026-03-03",
      "end_date": "2026-03-03",
      "done": false,
      "task_status": "inbox",
      "description": "",
      "comments": [],
      "estimated_hours": null,
      "task_type": null,
      "created_at": "2026-02-14T08:20:23.847787+00:00",
      "updated_at": "2026-02-14T08:20:23.847787+00:00",
      "dependencies": [
        "1771043105398-1771055966841"
      ],
      "include_weekends": false
    },
    {
      "id": "1771044296039-12",
      "project_id": 1771044296039,
      "name": "グリッジ採用LP 全体デザイン修正指示",
      "phase": "design",
      "assignee": "client",
      "start_date": "2026-04-24",
      "end_date": "2026-04-24",
      "done": false,
      "task_status": "todo",
      "description": "",
      "comments": [],
      "estimated_hours": null,
      "task_type": "milestone",
      "created_at": "2026-02-14T04:44:57.863188+00:00",
      "updated_at": "2026-02-14T04:44:57.863188+00:00",
      "dependencies": [],
      "include_weekends": false
    },
    {
      "id": "1771044296039-9",
      "project_id": 1771044296039,
      "name": "グリッジ採用LP 全体ページデザイン",
      "phase": "design",
      "assignee": "nakata",
      "start_date": "2026-04-13",
      "end_date": "2026-04-17",
      "done": false,
      "task_status": "todo",
      "description": "",
      "comments": [],
      "estimated_hours": null,
      "task_type": null,
      "created_at": "2026-02-14T04:44:57.863188+00:00",
      "updated_at": "2026-02-14T04:44:57.863188+00:00",
      "dependencies": [],
      "include_weekends": false
    },
    {
      "id": "t17710580695619hobt",
      "project_id": 1771039129808,
      "name": "津島福居分譲地：企画構成 (コピー)",
      "phase": "wire",
      "assignee": null,
      "start_date": "2026-03-02",
      "end_date": "2026-03-02",
      "done": false,
      "task_status": "inbox",
      "description": "",
      "comments": [],
      "estimated_hours": null,
      "task_type": null,
      "created_at": "2026-02-14T08:34:31.403179+00:00",
      "updated_at": "2026-02-14T08:34:31.403179+00:00",
      "dependencies": [],
      "include_weekends": false
    },
    {
      "id": "t1771058069561zxwn0",
      "project_id": 1771039129808,
      "name": "津島福居分譲地：WF作成 (コピー)",
      "phase": "wire",
      "assignee": null,
      "start_date": "2026-03-03",
      "end_date": "2026-03-03",
      "done": false,
      "task_status": "inbox",
      "description": "",
      "comments": [],
      "estimated_hours": null,
      "task_type": null,
      "created_at": "2026-02-14T08:34:31.403179+00:00",
      "updated_at": "2026-02-14T08:34:31.403179+00:00",
      "dependencies": [],
      "include_weekends": false
    },
    {
      "id": "t1771064860348ncxux",
      "project_id": 1771039129808,
      "name": "仏生山2イベントデザイン（バナー・LP） 2/2 ",
      "phase": "wire",
      "assignee": "nakata",
      "start_date": "2026-02-23",
      "end_date": "2026-02-23",
      "done": false,
      "task_status": "inbox",
      "description": "",
      "comments": [],
      "estimated_hours": null,
      "task_type": null,
      "created_at": "2026-02-14T10:27:44.702326+00:00",
      "updated_at": "2026-02-14T10:27:44.702326+00:00",
      "dependencies": [],
      "include_weekends": false
    },
    {
      "id": "1771039129808-1771042194391",
      "project_id": 1771039129808,
      "name": "松浜・藤原西町2/4棟デザイン（バナー）",
      "phase": "wire",
      "assignee": "nakata",
      "start_date": "2026-02-16",
      "end_date": "2026-02-17",
      "done": false,
      "task_status": "inbox",
      "description": "",
      "comments": [],
      "estimated_hours": null,
      "task_type": null,
      "created_at": "2026-02-14T04:09:56.256021+00:00",
      "updated_at": "2026-02-14T04:09:56.256021+00:00",
      "dependencies": [],
      "include_weekends": false
    },
    {
      "id": "t17710580695610xbx2",
      "project_id": 1771039129808,
      "name": "津島福居分譲地：LPデザイン (コピー)",
      "phase": "wire",
      "assignee": null,
      "start_date": "2026-03-04",
      "end_date": "2026-03-04",
      "done": false,
      "task_status": "inbox",
      "description": "",
      "comments": [],
      "estimated_hours": null,
      "task_type": null,
      "created_at": "2026-02-14T08:34:31.403179+00:00",
      "updated_at": "2026-02-14T08:34:31.403179+00:00",
      "dependencies": [],
      "include_weekends": false
    },
    {
      "id": "1771043105398-1771056079725",
      "project_id": 1771039129808,
      "name": "風の野学南用看板（1.82㎡ × 3.64㎡）",
      "phase": "wire",
      "assignee": null,
      "start_date": "2026-03-19",
      "end_date": "2026-03-20",
      "done": false,
      "task_status": "inbox",
      "description": "",
      "comments": [],
      "estimated_hours": null,
      "task_type": null,
      "created_at": "2026-02-14T08:01:23.003369+00:00",
      "updated_at": "2026-02-14T08:01:23.003369+00:00",
      "dependencies": [],
      "include_weekends": false
    },
    {
      "id": "t1771046257053",
      "project_id": 1771046274008,
      "name": "両備ホームズイベント全体管理調整 (コピー) (コピー)",
      "phase": "wire",
      "assignee": "fujii",
      "start_date": "2026-03-30",
      "end_date": "2026-04-03",
      "done": false,
      "task_status": "inbox",
      "description": "",
      "comments": [],
      "estimated_hours": 16,
      "task_type": null,
      "created_at": "2026-02-14T05:17:39.025673+00:00",
      "updated_at": "2026-02-14T05:17:39.025673+00:00",
      "dependencies": [],
      "include_weekends": false
    },
    {
      "id": "1771043105398-1771045953231",
      "project_id": 1771046274008,
      "name": "両備ホームズイベント全体管理調整",
      "phase": "wire",
      "assignee": "fujii",
      "start_date": "2026-02-16",
      "end_date": "2026-02-20",
      "done": false,
      "task_status": "inbox",
      "description": "",
      "comments": [],
      "estimated_hours": 16,
      "task_type": null,
      "created_at": "2026-02-14T05:12:35.221136+00:00",
      "updated_at": "2026-02-14T05:12:35.221136+00:00",
      "dependencies": [],
      "include_weekends": false
    },
    {
      "id": "t1771046156853",
      "project_id": 1771046274008,
      "name": "両備ホームズイベント全体管理調整 (コピー)",
      "phase": "wire",
      "assignee": "fujii",
      "start_date": "2026-03-09",
      "end_date": "2026-03-13",
      "done": false,
      "task_status": "inbox",
      "description": "",
      "comments": [],
      "estimated_hours": 16,
      "task_type": null,
      "created_at": "2026-02-14T05:16:00.802453+00:00",
      "updated_at": "2026-02-14T05:16:00.802453+00:00",
      "dependencies": [],
      "include_weekends": false
    },
    {
      "id": "t1771046135489",
      "project_id": 1771046274008,
      "name": "両備ホームズイベント全体管理調整 (コピー)",
      "phase": "wire",
      "assignee": "fujii",
      "start_date": "2026-02-23",
      "end_date": "2026-02-27",
      "done": false,
      "task_status": "inbox",
      "description": "",
      "comments": [],
      "estimated_hours": 16,
      "task_type": null,
      "created_at": "2026-02-14T05:15:38.873657+00:00",
      "updated_at": "2026-02-14T05:15:38.873657+00:00",
      "dependencies": [],
      "include_weekends": false
    },
    {
      "id": "t1771046145996",
      "project_id": 1771046274008,
      "name": "両備ホームズイベント全体管理調整 (コピー)",
      "phase": "wire",
      "assignee": "fujii",
      "start_date": "2026-03-02",
      "end_date": "2026-03-06",
      "done": false,
      "task_status": "inbox",
      "description": "",
      "comments": [],
      "estimated_hours": 16,
      "task_type": null,
      "created_at": "2026-02-14T05:15:50.262744+00:00",
      "updated_at": "2026-02-14T05:15:50.262744+00:00",
      "dependencies": [],
      "include_weekends": false
    },
    {
      "id": "t1771046177502",
      "project_id": 1771046274008,
      "name": "両備ホームズイベント全体管理調整 (コピー)",
      "phase": "wire",
      "assignee": "fujii",
      "start_date": "2026-03-16",
      "end_date": "2026-03-20",
      "done": false,
      "task_status": "inbox",
      "description": "",
      "comments": [],
      "estimated_hours": 16,
      "task_type": null,
      "created_at": "2026-02-14T05:16:19.48592+00:00",
      "updated_at": "2026-02-14T05:16:19.48592+00:00",
      "dependencies": [],
      "include_weekends": false
    },
    {
      "id": "1771062269488-1771062291451",
      "project_id": 1771062269488,
      "name": "小野歯科医院改修",
      "phase": "wire",
      "assignee": "imashige",
      "start_date": "2026-02-19",
      "end_date": "2026-02-20",
      "done": false,
      "task_status": "inbox",
      "description": "",
      "comments": [],
      "estimated_hours": null,
      "task_type": null,
      "created_at": "2026-02-14T09:44:53.341403+00:00",
      "updated_at": "2026-02-14T09:44:53.341403+00:00",
      "dependencies": [],
      "include_weekends": false
    },
    {
      "id": "1771043105398-1771056092320",
      "project_id": 1771039129808,
      "name": "屋根とお腹プロジェクトチラシ（A4両面）",
      "phase": "wire",
      "assignee": null,
      "start_date": "2026-03-16",
      "end_date": "2026-03-17",
      "done": false,
      "task_status": "inbox",
      "description": "",
      "comments": [],
      "estimated_hours": null,
      "task_type": null,
      "created_at": "2026-02-14T08:01:34.889966+00:00",
      "updated_at": "2026-02-14T08:01:34.889966+00:00",
      "dependencies": [],
      "include_weekends": false
    },
    {
      "id": "t1771057241322alvkd",
      "project_id": 1771039129808,
      "name": "津島福居分譲地：LPデザイン",
      "phase": "wire",
      "assignee": null,
      "start_date": "2026-03-04",
      "end_date": "2026-03-04",
      "done": false,
      "task_status": "inbox",
      "description": "",
      "comments": [],
      "estimated_hours": null,
      "task_type": null,
      "created_at": "2026-02-14T08:20:44.309558+00:00",
      "updated_at": "2026-02-14T08:20:44.309558+00:00",
      "dependencies": [
        "t1771057220792ad9n3"
      ],
      "include_weekends": false
    },
    {
      "id": "1771039129808-1771042221913",
      "project_id": 1771039129808,
      "name": "氷上イベントデザイン（バナー）",
      "phase": "wire",
      "assignee": "nakata",
      "start_date": "2026-02-18",
      "end_date": "2026-02-19",
      "done": false,
      "task_status": "inbox",
      "description": "",
      "comments": [],
      "estimated_hours": null,
      "task_type": null,
      "created_at": "2026-02-14T04:10:25.123173+00:00",
      "updated_at": "2026-02-14T04:10:25.123173+00:00",
      "dependencies": [],
      "include_weekends": false
    },
    {
      "id": "1771043105398-1771056079757",
      "project_id": 1771039129808,
      "name": "津島福居・津島新野、伊島町3エリア訴求チラシ（ポスティング）",
      "phase": "wire",
      "assignee": null,
      "start_date": "2026-03-09",
      "end_date": "2026-03-13",
      "done": false,
      "task_status": "inbox",
      "description": "",
      "comments": [],
      "estimated_hours": null,
      "task_type": null,
      "created_at": "2026-02-14T08:01:23.003369+00:00",
      "updated_at": "2026-02-14T08:01:23.003369+00:00",
      "dependencies": [],
      "include_weekends": false
    },
    {
      "id": "1771039129808-1771042194448",
      "project_id": 1771039129808,
      "name": "仏生山2イベントデザイン（バナー・LP） 1/2",
      "phase": "wire",
      "assignee": "nakata",
      "start_date": "2026-02-20",
      "end_date": "2026-02-20",
      "done": false,
      "task_status": "inbox",
      "description": "",
      "comments": [],
      "estimated_hours": null,
      "task_type": null,
      "created_at": "2026-02-14T04:09:56.256021+00:00",
      "updated_at": "2026-02-14T04:09:56.256021+00:00",
      "dependencies": [],
      "include_weekends": false
    },
    {
      "id": "t1771058069561mnxfa",
      "project_id": 1771039129808,
      "name": "津島福居分譲地：バナーデザイン (コピー)",
      "phase": "wire",
      "assignee": null,
      "start_date": "2026-03-05",
      "end_date": "2026-03-05",
      "done": false,
      "task_status": "inbox",
      "description": "",
      "comments": [],
      "estimated_hours": null,
      "task_type": null,
      "created_at": "2026-02-14T08:34:31.403179+00:00",
      "updated_at": "2026-02-14T08:34:31.403179+00:00",
      "dependencies": [],
      "include_weekends": false
    },
    {
      "id": "t1771057256847eierl",
      "project_id": 1771039129808,
      "name": "津島福居分譲地：バナーデザイン",
      "phase": "wire",
      "assignee": null,
      "start_date": "2026-03-05",
      "end_date": "2026-03-05",
      "done": false,
      "task_status": "inbox",
      "description": "",
      "comments": [],
      "estimated_hours": null,
      "task_type": null,
      "created_at": "2026-02-14T08:20:58.690662+00:00",
      "updated_at": "2026-02-14T08:20:58.690662+00:00",
      "dependencies": [
        "t1771057241322alvkd"
      ],
      "include_weekends": false
    },
    {
      "id": "1771043105398-1771056053033",
      "project_id": 1771039129808,
      "name": "土地訴求（土地をお探しの方へ：ブラッシュアップ）",
      "phase": "wire",
      "assignee": null,
      "start_date": "2026-03-09",
      "end_date": "2026-03-13",
      "done": false,
      "task_status": "inbox",
      "description": "",
      "comments": [],
      "estimated_hours": null,
      "task_type": null,
      "created_at": "2026-02-14T08:00:54.912075+00:00",
      "updated_at": "2026-02-14T08:00:54.912075+00:00",
      "dependencies": [],
      "include_weekends": false
    },
    {
      "id": "1771043105398-1771056171142",
      "project_id": 1771046274008,
      "name": "中田サポート余力",
      "phase": "wire",
      "assignee": "fujii",
      "start_date": "2026-02-19",
      "end_date": "2026-02-20",
      "done": false,
      "task_status": "inbox",
      "description": "",
      "comments": [],
      "estimated_hours": null,
      "task_type": null,
      "created_at": "2026-02-14T08:02:53.168561+00:00",
      "updated_at": "2026-02-14T08:02:53.168561+00:00",
      "dependencies": [],
      "include_weekends": false
    },
    {
      "id": "t1771046250034",
      "project_id": 1771046274008,
      "name": "両備ホームズイベント全体管理調整 (コピー) (コピー)",
      "phase": "wire",
      "assignee": "fujii",
      "start_date": "2026-03-23",
      "end_date": "2026-03-27",
      "done": false,
      "task_status": "inbox",
      "description": "",
      "comments": [],
      "estimated_hours": 16,
      "task_type": null,
      "created_at": "2026-02-14T05:17:32.563438+00:00",
      "updated_at": "2026-02-14T05:17:32.563438+00:00",
      "dependencies": [],
      "include_weekends": false
    }
  ],
  "members": [
    {
      "id": "shimizu",
      "name": "清水",
      "role": "営業・全体統括",
      "color": "#ef4444",
      "hpw": 40,
      "av": "清",
      "type": "internal",
      "sort_order": 0,
      "created_at": "2026-02-14T06:00:33.282659+00:00"
    },
    {
      "id": "imashige",
      "name": "今重",
      "role": "コンテンツ・企画",
      "color": "#8b5cf6",
      "hpw": 40,
      "av": "今",
      "type": "internal",
      "sort_order": 1,
      "created_at": "2026-02-14T06:00:33.282659+00:00"
    },
    {
      "id": "fujii",
      "name": "藤井",
      "role": "デザイン・撮影",
      "color": "#10b981",
      "hpw": 40,
      "av": "藤",
      "type": "internal",
      "sort_order": 2,
      "created_at": "2026-02-14T06:00:33.282659+00:00"
    },
    {
      "id": "nishitani",
      "name": "西谷",
      "role": "エンジニアリング",
      "color": "#0ea5e9",
      "hpw": 40,
      "av": "西",
      "type": "internal",
      "sort_order": 3,
      "created_at": "2026-02-14T06:00:33.282659+00:00"
    },
    {
      "id": "honda",
      "name": "本田",
      "role": "ディレクター(パート)",
      "color": "#f59e0b",
      "hpw": 20,
      "av": "本",
      "type": "internal",
      "sort_order": 4,
      "created_at": "2026-02-14T06:00:33.282659+00:00"
    },
    {
      "id": "nakata",
      "name": "中田",
      "role": "デザイン",
      "color": "#f97316",
      "hpw": 40,
      "av": "中",
      "type": "internal",
      "sort_order": 5,
      "created_at": "2026-02-14T06:00:33.282659+00:00"
    },
    {
      "id": "okada",
      "name": "岡田",
      "role": "プランナー",
      "color": "#64748b",
      "hpw": 20,
      "av": "岡",
      "type": "external",
      "sort_order": 6,
      "created_at": "2026-02-14T06:00:33.282659+00:00"
    },
    {
      "id": "client",
      "name": "クライアント",
      "role": "お客様",
      "color": "#64748b",
      "hpw": 40,
      "av": "客",
      "type": "external",
      "sort_order": 7,
      "created_at": "2026-02-14T06:00:33.282659+00:00"
    },
    {
      "id": "member_1771048866898",
      "name": "花菜",
      "role": "デザイナー",
      "color": "#64748b",
      "hpw": 20,
      "av": "花",
      "type": "external",
      "sort_order": 8,
      "created_at": "2026-02-14T06:01:30.480404+00:00"
    },
    {
      "id": "member_1771048895950",
      "name": "美咲",
      "role": "デザイナー",
      "color": "#64748b",
      "hpw": 20,
      "av": "美",
      "type": "external",
      "sort_order": 9,
      "created_at": "2026-02-14T06:01:44.650379+00:00"
    },
    {
      "id": "member_1771048904241",
      "name": "三宅",
      "role": "エンジニア",
      "color": "#64748b",
      "hpw": 20,
      "av": "三",
      "type": "external",
      "sort_order": 10,
      "created_at": "2026-02-14T06:01:53.081572+00:00"
    },
    {
      "id": "member_1771054314937",
      "name": "岸",
      "role": "ライター",
      "color": "#64748b",
      "hpw": 20,
      "av": "岸",
      "type": "external",
      "sort_order": 11,
      "created_at": "2026-02-14T07:32:03.530021+00:00"
    },
    {
      "id": "member_1771061146147",
      "name": "嶋村",
      "role": "デザイナー",
      "color": "#64748b",
      "hpw": 20,
      "av": "嶋",
      "type": "external",
      "sort_order": 12,
      "created_at": "2026-02-14T09:25:54.5608+00:00"
    }
  ],
  "stats": {
    "projectCount": 16,
    "taskCount": 161,
    "memberCount": 13
  }
}